{
"meta":{"test_sets":[],"test_metrics":[],"learn_metrics":[{"best_value":"Min","name":"RMSE"}],"launch_mode":"Train","parameters":"","iteration_count":1000,"learn_sets":["learn"],"name":"experiment"},
"iterations":[
{"learn":[14.9772428],"iteration":0,"passed_time":0.1446370045,"remaining_time":144.4923675},
{"learn":[14.58062402],"iteration":1,"passed_time":0.1454048184,"remaining_time":72.55700436},
{"learn":[14.2106],"iteration":2,"passed_time":0.1460396755,"remaining_time":48.53385217},
{"learn":[13.84355499],"iteration":3,"passed_time":0.146633899,"remaining_time":36.51184086},
{"learn":[13.47181581],"iteration":4,"passed_time":0.14724194,"remaining_time":29.30114605},
{"learn":[13.14085643],"iteration":5,"passed_time":0.1478368677,"remaining_time":24.49164108},
{"learn":[12.81807606],"iteration":6,"passed_time":0.1484337379,"remaining_time":21.05638597},
{"learn":[12.49903564],"iteration":7,"passed_time":0.1490887938,"remaining_time":18.48701043},
{"learn":[12.21712213],"iteration":8,"passed_time":0.149695521,"remaining_time":16.48314015},
{"learn":[11.91753998],"iteration":9,"passed_time":0.1503060341,"remaining_time":14.88029737},
{"learn":[11.61651421],"iteration":10,"passed_time":0.1509173767,"remaining_time":13.56884414},
{"learn":[11.33650695],"iteration":11,"passed_time":0.1515505975,"remaining_time":12.47766586},
{"learn":[11.12094771],"iteration":12,"passed_time":0.1521843531,"remaining_time":11.55430434},
{"learn":[10.8665444],"iteration":13,"passed_time":0.1527905527,"remaining_time":10.76082035},
{"learn":[10.63024225],"iteration":14,"passed_time":0.1533797182,"remaining_time":10.07193483},
{"learn":[10.38856403],"iteration":15,"passed_time":0.153978332,"remaining_time":9.469667417},
{"learn":[10.21636675],"iteration":16,"passed_time":0.1543573721,"remaining_time":8.925488044},
{"learn":[10.0138963],"iteration":17,"passed_time":0.1549480573,"remaining_time":8.453277348},
{"learn":[9.816391976],"iteration":18,"passed_time":0.1555453497,"remaining_time":8.031052004},
{"learn":[9.626962894],"iteration":19,"passed_time":0.1562525123,"remaining_time":7.656373103},
{"learn":[9.440704442],"iteration":20,"passed_time":0.1568468191,"remaining_time":7.312049331},
{"learn":[9.250852717],"iteration":21,"passed_time":0.1574390071,"remaining_time":6.9988795},
{"learn":[9.089422275],"iteration":22,"passed_time":0.158133748,"remaining_time":6.717246601},
{"learn":[8.916017209],"iteration":23,"passed_time":0.1587986495,"remaining_time":6.457811746},
{"learn":[8.766191154],"iteration":24,"passed_time":0.159427394,"remaining_time":6.217668364},
{"learn":[8.619848941],"iteration":25,"passed_time":0.1600369476,"remaining_time":5.995230269},
{"learn":[8.475875155],"iteration":26,"passed_time":0.1606528826,"remaining_time":5.789453881},
{"learn":[8.337288947],"iteration":27,"passed_time":0.1612721118,"remaining_time":5.598446165},
{"learn":[8.201038344],"iteration":28,"passed_time":0.1618665619,"remaining_time":5.419739019},
{"learn":[8.081972773],"iteration":29,"passed_time":0.1624861288,"remaining_time":5.253718165},
{"learn":[7.963803951],"iteration":30,"passed_time":0.1630853741,"remaining_time":5.097733145},
{"learn":[7.85367164],"iteration":31,"passed_time":0.1636890637,"remaining_time":4.951594177},
{"learn":[7.750852615],"iteration":32,"passed_time":0.1642898827,"remaining_time":4.814191411},
{"learn":[7.647806053],"iteration":33,"passed_time":0.1649230143,"remaining_time":4.685753877},
{"learn":[7.53996634],"iteration":34,"passed_time":0.1655309109,"remaining_time":4.563923687},
{"learn":[7.439914969],"iteration":35,"passed_time":0.1661400521,"remaining_time":4.448861394},
{"learn":[7.350432522],"iteration":36,"passed_time":0.1667399258,"remaining_time":4.339744555},
{"learn":[7.252557981],"iteration":37,"passed_time":0.1673330057,"remaining_time":4.236167144},
{"learn":[7.161589494],"iteration":38,"passed_time":0.1679419351,"remaining_time":4.138261528},
{"learn":[7.082044999],"iteration":39,"passed_time":0.1685305651,"remaining_time":4.044733563},
{"learn":[7.004628637],"iteration":40,"passed_time":0.1691424481,"remaining_time":3.956283114},
{"learn":[6.931071461],"iteration":41,"passed_time":0.1697360042,"remaining_time":3.871597429},
{"learn":[6.858752733],"iteration":42,"passed_time":0.1703356806,"remaining_time":3.790959218},
{"learn":[6.800388309],"iteration":43,"passed_time":0.170925163,"remaining_time":3.713737632},
{"learn":[6.732084185],"iteration":44,"passed_time":0.1715247031,"remaining_time":3.640135365},
{"learn":[6.669393641],"iteration":45,"passed_time":0.1721717667,"remaining_time":3.570692727},
{"learn":[6.608760431],"iteration":46,"passed_time":0.1728724988,"remaining_time":3.505265773},
{"learn":[6.548920779],"iteration":47,"passed_time":0.1735244671,"remaining_time":3.441568598},
{"learn":[6.49472584],"iteration":48,"passed_time":0.1741865834,"remaining_time":3.38064165},
{"learn":[6.4351889],"iteration":49,"passed_time":0.1748785546,"remaining_time":3.322692538},
{"learn":[6.384975664],"iteration":50,"passed_time":0.1754960795,"remaining_time":3.265603519},
{"learn":[6.333077817],"iteration":51,"passed_time":0.1760986227,"remaining_time":3.210413353},
{"learn":[6.284794515],"iteration":52,"passed_time":0.1767078293,"remaining_time":3.157402158},
{"learn":[6.247649549],"iteration":53,"passed_time":0.1773140475,"remaining_time":3.106279425},
{"learn":[6.204432836],"iteration":54,"passed_time":0.178015189,"remaining_time":3.058624611},
{"learn":[6.161524721],"iteration":55,"passed_time":0.1786348503,"remaining_time":3.011273191},
{"learn":[6.120092495],"iteration":56,"passed_time":0.1792386322,"remaining_time":2.965298774},
{"learn":[6.08004572],"iteration":57,"passed_time":0.1798368406,"remaining_time":2.920798342},
{"learn":[6.04009235],"iteration":58,"passed_time":0.1804507305,"remaining_time":2.878036226},
{"learn":[6.00757713],"iteration":59,"passed_time":0.1810539996,"remaining_time":2.83651266},
{"learn":[5.970933357],"iteration":60,"passed_time":0.1816513182,"remaining_time":2.796239144},
{"learn":[5.939163035],"iteration":61,"passed_time":0.1822578546,"remaining_time":2.757384961},
{"learn":[5.915433795],"iteration":62,"passed_time":0.1828698126,"remaining_time":2.719825625},
{"learn":[5.890322087],"iteration":63,"passed_time":0.1834868537,"remaining_time":2.683495235},
{"learn":[5.859380893],"iteration":64,"passed_time":0.1841046771,"remaining_time":2.648274971},
{"learn":[5.831796289],"iteration":65,"passed_time":0.1846810232,"remaining_time":2.613516298},
{"learn":[5.800526431],"iteration":66,"passed_time":0.1852918927,"remaining_time":2.580258745},
{"learn":[5.77322099],"iteration":67,"passed_time":0.1859295898,"remaining_time":2.548329084},
{"learn":[5.747296169],"iteration":68,"passed_time":0.1865143603,"remaining_time":2.516592311},
{"learn":[5.726269148],"iteration":69,"passed_time":0.1871547572,"remaining_time":2.486484631},
{"learn":[5.701650842],"iteration":70,"passed_time":0.1878036942,"remaining_time":2.457318759},
{"learn":[5.682288016],"iteration":71,"passed_time":0.1884113659,"remaining_time":2.428413161},
{"learn":[5.662936108],"iteration":72,"passed_time":0.1890258708,"remaining_time":2.40036962},
{"learn":[5.643304074],"iteration":73,"passed_time":0.1896324196,"remaining_time":2.372967846},
{"learn":[5.620493459],"iteration":74,"passed_time":0.1902203799,"remaining_time":2.346051352},
{"learn":[5.601468004],"iteration":75,"passed_time":0.1908299911,"remaining_time":2.320090945},
{"learn":[5.582291489],"iteration":76,"passed_time":0.1914341638,"remaining_time":2.294723808},
{"learn":[5.562003249],"iteration":77,"passed_time":0.1920331884,"remaining_time":2.269930765},
{"learn":[5.543017433],"iteration":78,"passed_time":0.1926384073,"remaining_time":2.245822444},
{"learn":[5.526760819],"iteration":79,"passed_time":0.193255302,"remaining_time":2.222435973},
{"learn":[5.512737509],"iteration":80,"passed_time":0.193837246,"remaining_time":2.199215174},
{"learn":[5.495127655],"iteration":81,"passed_time":0.1944305811,"remaining_time":2.176674066},
{"learn":[5.47646966],"iteration":82,"passed_time":0.1950656631,"remaining_time":2.155123049},
{"learn":[5.457071114],"iteration":83,"passed_time":0.1956604483,"remaining_time":2.133630603},
{"learn":[5.445745608],"iteration":84,"passed_time":0.1961441095,"remaining_time":2.111433649},
{"learn":[5.433127958],"iteration":85,"passed_time":0.1967557341,"remaining_time":2.091101639},
{"learn":[5.425946844],"iteration":86,"passed_time":0.1971699884,"remaining_time":2.069151717},
{"learn":[5.412127343],"iteration":87,"passed_time":0.1977763295,"remaining_time":2.049681961},
{"learn":[5.398652853],"iteration":88,"passed_time":0.1983873812,"remaining_time":2.030684317},
{"learn":[5.382738657],"iteration":89,"passed_time":0.1989949861,"remaining_time":2.012060415},
{"learn":[5.369324869],"iteration":90,"passed_time":0.1996037874,"remaining_time":1.993844426},
{"learn":[5.357410056],"iteration":91,"passed_time":0.2001969454,"remaining_time":1.975856809},
{"learn":[5.351374737],"iteration":92,"passed_time":0.2005891259,"remaining_time":1.956283196},
{"learn":[5.337697939],"iteration":93,"passed_time":0.2012133593,"remaining_time":1.939354293},
{"learn":[5.324920798],"iteration":94,"passed_time":0.2018458425,"remaining_time":1.922847236},
{"learn":[5.313116879],"iteration":95,"passed_time":0.2024522731,"remaining_time":1.906425572},
{"learn":[5.30329834],"iteration":96,"passed_time":0.2030513514,"remaining_time":1.89026155},
{"learn":[5.292656177],"iteration":97,"passed_time":0.2036235759,"remaining_time":1.874168015},
{"learn":[5.279161916],"iteration":98,"passed_time":0.2042233522,"remaining_time":1.858638791},
{"learn":[5.269663447],"iteration":99,"passed_time":0.2048162306,"remaining_time":1.843346076},
{"learn":[5.253624676],"iteration":100,"passed_time":0.2054133216,"remaining_time":1.828381942},
{"learn":[5.240554551],"iteration":101,"passed_time":0.2059962749,"remaining_time":1.813575048},
{"learn":[5.233512756],"iteration":102,"passed_time":0.2065939555,"remaining_time":1.799172602},
{"learn":[5.224711219],"iteration":103,"passed_time":0.2071792897,"remaining_time":1.784929265},
{"learn":[5.216370987],"iteration":104,"passed_time":0.2077763504,"remaining_time":1.771046034},
{"learn":[5.206578085],"iteration":105,"passed_time":0.208380322,"remaining_time":1.757471772},
{"learn":[5.199043005],"iteration":106,"passed_time":0.2089719149,"remaining_time":1.744036636},
{"learn":[5.189026842],"iteration":107,"passed_time":0.2095733886,"remaining_time":1.73092095},
{"learn":[5.18023674],"iteration":108,"passed_time":0.2101627842,"remaining_time":1.717936153},
{"learn":[5.17173701],"iteration":109,"passed_time":0.2107695141,"remaining_time":1.705316978},
{"learn":[5.164266895],"iteration":110,"passed_time":0.2113825582,"remaining_time":1.692964813},
{"learn":[5.15490828],"iteration":111,"passed_time":0.2119800493,"remaining_time":1.680698962},
{"learn":[5.146791206],"iteration":112,"passed_time":0.2125900266,"remaining_time":1.668737642},
{"learn":[5.136578102],"iteration":113,"passed_time":0.2131910932,"remaining_time":1.656906215},
{"learn":[5.130651219],"iteration":114,"passed_time":0.2137635308,"remaining_time":1.64504978},
{"learn":[5.12445917],"iteration":115,"passed_time":0.2143455451,"remaining_time":1.633460878},
{"learn":[5.11696168],"iteration":116,"passed_time":0.2149553904,"remaining_time":1.622270169},
{"learn":[5.11327594],"iteration":117,"passed_time":0.2155608004,"remaining_time":1.611225644},
{"learn":[5.107615387],"iteration":118,"passed_time":0.2161415619,"remaining_time":1.600174084},
{"learn":[5.102325501],"iteration":119,"passed_time":0.2168269414,"remaining_time":1.590064237},
{"learn":[5.094060824],"iteration":120,"passed_time":0.2174608405,"remaining_time":1.579736189},
{"learn":[5.089176571],"iteration":121,"passed_time":0.2180850109,"remaining_time":1.569497045},
{"learn":[5.083243415],"iteration":122,"passed_time":0.2187082897,"remaining_time":1.559407887},
{"learn":[5.077864524],"iteration":123,"passed_time":0.2193002941,"remaining_time":1.549250465},
{"learn":[5.072612637],"iteration":124,"passed_time":0.2198849548,"remaining_time":1.539194683},
{"learn":[5.069820088],"iteration":125,"passed_time":0.2202699427,"remaining_time":1.527904205},
{"learn":[5.065142668],"iteration":126,"passed_time":0.220889719,"remaining_time":1.518399407},
{"learn":[5.059486207],"iteration":127,"passed_time":0.2214855713,"remaining_time":1.508870454},
{"learn":[5.052920704],"iteration":128,"passed_time":0.2220992211,"remaining_time":1.499600167},
{"learn":[5.045694355],"iteration":129,"passed_time":0.2227438002,"remaining_time":1.490670048},
{"learn":[5.042237848],"iteration":130,"passed_time":0.2231228968,"remaining_time":1.480105323},
{"learn":[5.037571422],"iteration":131,"passed_time":0.2237148362,"remaining_time":1.471094529},
{"learn":[5.030072696],"iteration":132,"passed_time":0.2243330323,"remaining_time":1.462381496},
{"learn":[5.026978372],"iteration":133,"passed_time":0.2249206062,"remaining_time":1.45359138},
{"learn":[5.018825637],"iteration":134,"passed_time":0.2255122394,"remaining_time":1.444948793},
{"learn":[5.008373662],"iteration":135,"passed_time":0.2261326132,"remaining_time":1.43660719},
{"learn":[5.003862016],"iteration":136,"passed_time":0.2267990574,"remaining_time":1.428668515},
{"learn":[4.997958071],"iteration":137,"passed_time":0.2274123178,"remaining_time":1.420503028},
{"learn":[4.99268892],"iteration":138,"passed_time":0.2280260458,"remaining_time":1.412449104},
{"learn":[4.987758411],"iteration":139,"passed_time":0.2286258355,"remaining_time":1.404415847},
{"learn":[4.983115185],"iteration":140,"passed_time":0.2293573501,"remaining_time":1.397290523},
{"learn":[4.978910231],"iteration":141,"passed_time":0.2299979391,"remaining_time":1.389705858},
{"learn":[4.973949677],"iteration":142,"passed_time":0.230589759,"remaining_time":1.381926038},
{"learn":[4.969866966],"iteration":143,"passed_time":0.2312023641,"remaining_time":1.374369609},
{"learn":[4.968732001],"iteration":144,"passed_time":0.2315164574,"remaining_time":1.365148766},
{"learn":[4.964915607],"iteration":145,"passed_time":0.2321011201,"remaining_time":1.357632579},
{"learn":[4.960838876],"iteration":146,"passed_time":0.2327056465,"remaining_time":1.350325962},
{"learn":[4.955695311],"iteration":147,"passed_time":0.2332895575,"remaining_time":1.342991236},
{"learn":[4.94957618],"iteration":148,"passed_time":0.2338788663,"remaining_time":1.335777954},
{"learn":[4.946971217],"iteration":149,"passed_time":0.2346475531,"remaining_time":1.329669467},
{"learn":[4.942877192],"iteration":150,"passed_time":0.2352856627,"remaining_time":1.322897534},
{"learn":[4.938252055],"iteration":151,"passed_time":0.2358813126,"remaining_time":1.315969428},
{"learn":[4.932220579],"iteration":152,"passed_time":0.2365085804,"remaining_time":1.309299135},
{"learn":[4.927192643],"iteration":153,"passed_time":0.2371120958,"remaining_time":1.302576838},
{"learn":[4.921979046],"iteration":154,"passed_time":0.2377097918,"remaining_time":1.295901768},
{"learn":[4.916189751],"iteration":155,"passed_time":0.2383089679,"remaining_time":1.289312621},
{"learn":[4.912446286],"iteration":156,"passed_time":0.2389077948,"remaining_time":1.282797904},
{"learn":[4.909912581],"iteration":157,"passed_time":0.2395158233,"remaining_time":1.276407109},
{"learn":[4.904657216],"iteration":158,"passed_time":0.240119674,"remaining_time":1.270066955},
{"learn":[4.90046448],"iteration":159,"passed_time":0.2407285255,"remaining_time":1.263824759},
{"learn":[4.895475987],"iteration":160,"passed_time":0.2413267395,"remaining_time":1.257597108},
{"learn":[4.892099193],"iteration":161,"passed_time":0.2419329656,"remaining_time":1.251480402},
{"learn":[4.888246408],"iteration":162,"passed_time":0.2425020451,"remaining_time":1.245240563},
{"learn":[4.884412746],"iteration":163,"passed_time":0.2430895188,"remaining_time":1.239163645},
{"learn":[4.87993796],"iteration":164,"passed_time":0.2436706804,"remaining_time":1.233121322},
{"learn":[4.875279318],"iteration":165,"passed_time":0.2442661329,"remaining_time":1.227216596},
{"learn":[4.870437682],"iteration":166,"passed_time":0.2448813248,"remaining_time":1.221473914},
{"learn":[4.864717068],"iteration":167,"passed_time":0.2454796014,"remaining_time":1.215708502},
{"learn":[4.861587629],"iteration":168,"passed_time":0.2461024064,"remaining_time":1.21012485},
{"learn":[4.859044265],"iteration":169,"passed_time":0.2466975273,"remaining_time":1.204464398},
{"learn":[4.853533439],"iteration":170,"passed_time":0.2473044136,"remaining_time":1.198920227},
{"learn":[4.849121924],"iteration":171,"passed_time":0.2478991471,"remaining_time":1.193374964},
{"learn":[4.84420945],"iteration":172,"passed_time":0.2485488878,"remaining_time":1.188149885},
{"learn":[4.841069546],"iteration":173,"passed_time":0.2492338044,"remaining_time":1.183144382},
{"learn":[4.839021108],"iteration":174,"passed_time":0.249865373,"remaining_time":1.177936758},
{"learn":[4.836281663],"iteration":175,"passed_time":0.2504625222,"remaining_time":1.17261999},
{"learn":[4.832079393],"iteration":176,"passed_time":0.2510619307,"remaining_time":1.167367056},
{"learn":[4.828898318],"iteration":177,"passed_time":0.251659896,"remaining_time":1.162159744},
{"learn":[4.824744164],"iteration":178,"passed_time":0.2522627829,"remaining_time":1.157026507},
{"learn":[4.820467545],"iteration":179,"passed_time":0.2528590674,"remaining_time":1.151913529},
{"learn":[4.818797449],"iteration":180,"passed_time":0.2534280717,"remaining_time":1.146727021},
{"learn":[4.813231995],"iteration":181,"passed_time":0.2540227705,"remaining_time":1.141706738},
{"learn":[4.808330248],"iteration":182,"passed_time":0.2546209004,"remaining_time":1.13675014},
{"learn":[4.805347314],"iteration":183,"passed_time":0.2552095057,"remaining_time":1.131798677},
{"learn":[4.800898205],"iteration":184,"passed_time":0.2557857698,"remaining_time":1.126840013},
{"learn":[4.800693756],"iteration":185,"passed_time":0.2560897007,"remaining_time":1.120736647},
{"learn":[4.797826431],"iteration":186,"passed_time":0.2566948532,"remaining_time":1.116004896},
{"learn":[4.79448598],"iteration":187,"passed_time":0.2572902526,"remaining_time":1.111274921},
{"learn":[4.791208836],"iteration":188,"passed_time":0.2578863815,"remaining_time":1.106591827},
{"learn":[4.788627889],"iteration":189,"passed_time":0.2585097812,"remaining_time":1.102068014},
{"learn":[4.782629775],"iteration":190,"passed_time":0.2591014006,"remaining_time":1.097450435},
{"learn":[4.78071494],"iteration":191,"passed_time":0.2596928451,"remaining_time":1.092874057},
{"learn":[4.776117354],"iteration":192,"passed_time":0.2602814153,"remaining_time":1.088326954},
{"learn":[4.773437298],"iteration":193,"passed_time":0.2608655873,"remaining_time":1.083802389},
{"learn":[4.771914102],"iteration":194,"passed_time":0.2614573032,"remaining_time":1.07934938},
{"learn":[4.76731897],"iteration":195,"passed_time":0.2620911239,"remaining_time":1.075108488},
{"learn":[4.762754929],"iteration":196,"passed_time":0.2626825078,"remaining_time":1.070731237},
{"learn":[4.760165726],"iteration":197,"passed_time":0.2633127251,"remaining_time":1.066549523},
{"learn":[4.754358649],"iteration":198,"passed_time":0.2639691811,"remaining_time":1.062509116},
{"learn":[4.750352668],"iteration":199,"passed_time":0.2645738394,"remaining_time":1.058295358},
{"learn":[4.746149207],"iteration":200,"passed_time":0.2651652677,"remaining_time":1.05406492},
{"learn":[4.742172381],"iteration":201,"passed_time":0.265756506,"remaining_time":1.049869761},
{"learn":[4.738961448],"iteration":202,"passed_time":0.2663444487,"remaining_time":1.045697171},
{"learn":[4.735518832],"iteration":203,"passed_time":0.2669410686,"remaining_time":1.041593582},
{"learn":[4.732397017],"iteration":204,"passed_time":0.2675541802,"remaining_time":1.037588162},
{"learn":[4.729912971],"iteration":205,"passed_time":0.2681438238,"remaining_time":1.033525224},
{"learn":[4.725651054],"iteration":206,"passed_time":0.2687438518,"remaining_time":1.029535625},
{"learn":[4.723875673],"iteration":207,"passed_time":0.269342397,"remaining_time":1.025572973},
{"learn":[4.721368761],"iteration":208,"passed_time":0.2699310691,"remaining_time":1.021605147},
{"learn":[4.717409579],"iteration":209,"passed_time":0.270514332,"remaining_time":1.017649154},
{"learn":[4.714875945],"iteration":210,"passed_time":0.2711520722,"remaining_time":1.013928839},
{"learn":[4.712167554],"iteration":211,"passed_time":0.2717596661,"remaining_time":1.010125551},
{"learn":[4.710758721],"iteration":212,"passed_time":0.2723489418,"remaining_time":1.006284588},
{"learn":[4.707338633],"iteration":213,"passed_time":0.2729684816,"remaining_time":1.002585171},
{"learn":[4.703693672],"iteration":214,"passed_time":0.2735565614,"remaining_time":0.9987995381},
{"learn":[4.698379257],"iteration":215,"passed_time":0.2741735673,"remaining_time":0.9951485037},
{"learn":[4.695274313],"iteration":216,"passed_time":0.2747828293,"remaining_time":0.9914974902},
{"learn":[4.693384047],"iteration":217,"passed_time":0.2753600102,"remaining_time":0.9877593025},
{"learn":[4.690503714],"iteration":218,"passed_time":0.2759392272,"remaining_time":0.984057244},
{"learn":[4.687972529],"iteration":219,"passed_time":0.2765419774,"remaining_time":0.9804670107},
{"learn":[4.684386769],"iteration":220,"passed_time":0.2772418375,"remaining_time":0.9772461149},
{"learn":[4.681317658],"iteration":221,"passed_time":0.2779063319,"remaining_time":0.9739239921},
{"learn":[4.680798229],"iteration":222,"passed_time":0.2785555082,"remaining_time":0.9705723314},
{"learn":[4.678253305],"iteration":223,"passed_time":0.2791807289,"remaining_time":0.9671618108},
{"learn":[4.676578697],"iteration":224,"passed_time":0.2797844415,"remaining_time":0.9637019653},
{"learn":[4.672698336],"iteration":225,"passed_time":0.280396049,"remaining_time":0.9602944332},
{"learn":[4.666763765],"iteration":226,"passed_time":0.2809922612,"remaining_time":0.9568591096},
{"learn":[4.664372282],"iteration":227,"passed_time":0.2815969707,"remaining_time":0.9534774623},
{"learn":[4.662357955],"iteration":228,"passed_time":0.2821916185,"remaining_time":0.9500861915},
{"learn":[4.65948583],"iteration":229,"passed_time":0.2827734134,"remaining_time":0.9466762101},
{"learn":[4.655039683],"iteration":230,"passed_time":0.283445824,"remaining_time":0.943592375},
{"learn":[4.651613722],"iteration":231,"passed_time":0.2840437517,"remaining_time":0.9402827643},
{"learn":[4.650272344],"iteration":232,"passed_time":0.2846304493,"remaining_time":0.9369594618},
{"learn":[4.648668721],"iteration":233,"passed_time":0.2852279046,"remaining_time":0.9336947646},
{"learn":[4.646321051],"iteration":234,"passed_time":0.2858055479,"remaining_time":0.9303882729},
{"learn":[4.641224189],"iteration":235,"passed_time":0.2863904802,"remaining_time":0.9271285038},
{"learn":[4.638461164],"iteration":236,"passed_time":0.2869954305,"remaining_time":0.9239557531},
{"learn":[4.633895237],"iteration":237,"passed_time":0.2875856178,"remaining_time":0.9207573142},
{"learn":[4.630173347],"iteration":238,"passed_time":0.288187795,"remaining_time":0.9176188785},
{"learn":[4.624148289],"iteration":239,"passed_time":0.288782326,"remaining_time":0.9144773656},
{"learn":[4.622162247],"iteration":240,"passed_time":0.2893888324,"remaining_time":0.9113947046},
{"learn":[4.621637216],"iteration":241,"passed_time":0.2899524906,"remaining_time":0.9081982971},
{"learn":[4.616031134],"iteration":242,"passed_time":0.2905414906,"remaining_time":0.9051025035},
{"learn":[4.61049669],"iteration":243,"passed_time":0.2911383174,"remaining_time":0.9020515081},
{"learn":[4.605249749],"iteration":244,"passed_time":0.2919100329,"remaining_time":0.899559489},
{"learn":[4.603854581],"iteration":245,"passed_time":0.2926130965,"remaining_time":0.8968710357},
{"learn":[4.600576923],"iteration":246,"passed_time":0.2937435339,"remaining_time":0.8955015425},
{"learn":[4.597131776],"iteration":247,"passed_time":0.2944851189,"remaining_time":0.8929548767},
{"learn":[4.593581219],"iteration":248,"passed_time":0.2955732906,"remaining_time":0.8914680373},
{"learn":[4.591646433],"iteration":249,"passed_time":0.2962224938,"remaining_time":0.8886674815},
{"learn":[4.588517352],"iteration":250,"passed_time":0.2968338712,"remaining_time":0.8857711934},
{"learn":[4.582401126],"iteration":251,"passed_time":0.2974430819,"remaining_time":0.8828866083},
{"learn":[4.577305976],"iteration":252,"passed_time":0.2980493439,"remaining_time":0.8800113039},
{"learn":[4.572769096],"iteration":253,"passed_time":0.2986494239,"remaining_time":0.8771357096},
{"learn":[4.567781082],"iteration":254,"passed_time":0.2992463196,"remaining_time":0.8742686593},
{"learn":[4.564467296],"iteration":255,"passed_time":0.2998549094,"remaining_time":0.8714533306},
{"learn":[4.55978477],"iteration":256,"passed_time":0.3004889274,"remaining_time":0.868728689},
{"learn":[4.553904394],"iteration":257,"passed_time":0.3010910213,"remaining_time":0.865928441},
{"learn":[4.549449547],"iteration":258,"passed_time":0.3016956289,"remaining_time":0.8631523591},
{"learn":[4.544715653],"iteration":259,"passed_time":0.3022845575,"remaining_time":0.8603483561},
{"learn":[4.541564499],"iteration":260,"passed_time":0.3028819529,"remaining_time":0.8575852997},
{"learn":[4.539109831],"iteration":261,"passed_time":0.3034934829,"remaining_time":0.8548785892},
{"learn":[4.538052588],"iteration":262,"passed_time":0.3040495287,"remaining_time":0.8520323295},
{"learn":[4.533689808],"iteration":263,"passed_time":0.3046483022,"remaining_time":0.8493225395},
{"learn":[4.531063551],"iteration":264,"passed_time":0.3052619228,"remaining_time":0.8466698613},
{"learn":[4.529101779],"iteration":265,"passed_time":0.3059406031,"remaining_time":0.8442120401},
{"learn":[4.527213585],"iteration":266,"passed_time":0.3066193957,"remaining_time":0.841767854},
{"learn":[4.524267756],"iteration":267,"passed_time":0.3072315923,"remaining_time":0.8391549461},
{"learn":[4.520769327],"iteration":268,"passed_time":0.3078164664,"remaining_time":0.8364826653},
{"learn":[4.513974002],"iteration":269,"passed_time":0.3084270563,"remaining_time":0.8338953744},
{"learn":[4.512280051],"iteration":270,"passed_time":0.3090529963,"remaining_time":0.8313639642},
{"learn":[4.509349512],"iteration":271,"passed_time":0.3096396384,"remaining_time":0.8287413851},
{"learn":[4.508898718],"iteration":272,"passed_time":0.3102097964,"remaining_time":0.826089824},
{"learn":[4.505532789],"iteration":273,"passed_time":0.310846636,"remaining_time":0.8236301378},
{"learn":[4.501961136],"iteration":274,"passed_time":0.3114673762,"remaining_time":0.8211412646},
{"learn":[4.496029386],"iteration":275,"passed_time":0.3120990019,"remaining_time":0.8186944833},
{"learn":[4.491686185],"iteration":276,"passed_time":0.3127031492,"remaining_time":0.8161890861},
{"learn":[4.487352185],"iteration":277,"passed_time":0.3133074731,"remaining_time":0.8136978257},
{"learn":[4.483421544],"iteration":278,"passed_time":0.3139130897,"remaining_time":0.8112234325},
{"learn":[4.478446474],"iteration":279,"passed_time":0.3145279103,"remaining_time":0.8087860552},
{"learn":[4.476640934],"iteration":280,"passed_time":0.3151053925,"remaining_time":0.806266111},
{"learn":[4.472447261],"iteration":281,"passed_time":0.3157128669,"remaining_time":0.8038363066},
{"learn":[4.467415269],"iteration":282,"passed_time":0.3164065744,"remaining_time":0.801637858},
{"learn":[4.466207575],"iteration":283,"passed_time":0.3169905143,"remaining_time":0.7991732684},
{"learn":[4.461497522],"iteration":284,"passed_time":0.3176064631,"remaining_time":0.7968021792},
{"learn":[4.458971486],"iteration":285,"passed_time":0.3181872572,"remaining_time":0.7943556003},
{"learn":[4.454446295],"iteration":286,"passed_time":0.3187926621,"remaining_time":0.791983164},
{"learn":[4.452209587],"iteration":287,"passed_time":0.319389075,"remaining_time":0.7896007688},
{"learn":[4.450253852],"iteration":288,"passed_time":0.3199812861,"remaining_time":0.7872203959},
{"learn":[4.445729606],"iteration":289,"passed_time":0.3206839558,"remaining_time":0.7851227884},
{"learn":[4.441985214],"iteration":290,"passed_time":0.3213177713,"remaining_time":0.7828670099},
{"learn":[4.438328761],"iteration":291,"passed_time":0.322016494,"remaining_time":0.7807797184},
{"learn":[4.432877836],"iteration":292,"passed_time":0.322633687,"remaining_time":0.7785051764},
{"learn":[4.427197949],"iteration":293,"passed_time":0.3232381128,"remaining_time":0.7762112504},
{"learn":[4.422701373],"iteration":294,"passed_time":0.3238620125,"remaining_time":0.7739753179},
{"learn":[4.422330789],"iteration":295,"passed_time":0.3244383093,"remaining_time":0.77163706},
{"learn":[4.418732731],"iteration":296,"passed_time":0.3250541603,"remaining_time":0.7694042919},
{"learn":[4.415910142],"iteration":297,"passed_time":0.3256390593,"remaining_time":0.7671094617},
{"learn":[4.415010084],"iteration":298,"passed_time":0.326206315,"remaining_time":0.764784705},
{"learn":[4.411282449],"iteration":299,"passed_time":0.3268279419,"remaining_time":0.762598531},
{"learn":[4.40928347],"iteration":300,"passed_time":0.3274299045,"remaining_time":0.7603770872},
{"learn":[4.406985601],"iteration":301,"passed_time":0.3280107035,"remaining_time":0.7581174538},
{"learn":[4.405072231],"iteration":302,"passed_time":0.3286214683,"remaining_time":0.755937833},
{"learn":[4.40362646],"iteration":303,"passed_time":0.329209503,"remaining_time":0.7537164937},
{"learn":[4.39645676],"iteration":304,"passed_time":0.3298181744,"remaining_time":0.7515528893},
{"learn":[4.393696852],"iteration":305,"passed_time":0.3304124785,"remaining_time":0.749366863},
{"learn":[4.389530282],"iteration":306,"passed_time":0.3310134384,"remaining_time":0.7472062306},
{"learn":[4.384320313],"iteration":307,"passed_time":0.3316094976,"remaining_time":0.7450447155},
{"learn":[4.383908585],"iteration":308,"passed_time":0.332193731,"remaining_time":0.742866887},
{"learn":[4.383663085],"iteration":309,"passed_time":0.3327536294,"remaining_time":0.7406451752},
{"learn":[4.381879428],"iteration":310,"passed_time":0.3333520824,"remaining_time":0.7385195651},
{"learn":[4.378798094],"iteration":311,"passed_time":0.3339683999,"remaining_time":0.7364431383},
{"learn":[4.376772633],"iteration":312,"passed_time":0.3345448717,"remaining_time":0.7342885843},
{"learn":[4.371411656],"iteration":313,"passed_time":0.3352188433,"remaining_time":0.7323570907},
{"learn":[4.370631251],"iteration":314,"passed_time":0.3358239781,"remaining_time":0.730283889},
{"learn":[4.369272104],"iteration":315,"passed_time":0.3364250317,"remaining_time":0.7282111445},
{"learn":[4.364720778],"iteration":316,"passed_time":0.3370079895,"remaining_time":0.7261086966},
{"learn":[4.36023585],"iteration":317,"passed_time":0.3376119642,"remaining_time":0.7240608792},
{"learn":[4.355421029],"iteration":318,"passed_time":0.3382215657,"remaining_time":0.7220341262},
{"learn":[4.355189036],"iteration":319,"passed_time":0.3387772107,"remaining_time":0.7199015727},
{"learn":[4.353955156],"iteration":320,"passed_time":0.3393886305,"remaining_time":0.7178968227},
{"learn":[4.348891476],"iteration":321,"passed_time":0.3399993863,"remaining_time":0.7158993289},
{"learn":[4.346265461],"iteration":322,"passed_time":0.3406103887,"remaining_time":0.7139109385},
{"learn":[4.343570771],"iteration":323,"passed_time":0.3412100544,"remaining_time":0.7119073976},
{"learn":[4.341599742],"iteration":324,"passed_time":0.3417955305,"remaining_time":0.709883025},
{"learn":[4.337306422],"iteration":325,"passed_time":0.3423935923,"remaining_time":0.7078935006},
{"learn":[4.332591615],"iteration":326,"passed_time":0.3429968714,"remaining_time":0.7059232246},
{"learn":[4.331502062],"iteration":327,"passed_time":0.3436839844,"remaining_time":0.7041330411},
{"learn":[4.325610832],"iteration":328,"passed_time":0.344289757,"remaining_time":0.7021836685},
{"learn":[4.32095826],"iteration":329,"passed_time":0.3448946384,"remaining_time":0.7002406295},
{"learn":[4.318689176],"iteration":330,"passed_time":0.3454835178,"remaining_time":0.6982733335},
{"learn":[4.317267186],"iteration":331,"passed_time":0.346079563,"remaining_time":0.6963287592},
{"learn":[4.311460781],"iteration":332,"passed_time":0.3466907806,"remaining_time":0.6944226746},
{"learn":[4.306863734],"iteration":333,"passed_time":0.3472847131,"remaining_time":0.692489877},
{"learn":[4.301969409],"iteration":334,"passed_time":0.3478881145,"remaining_time":0.690583869},
{"learn":[4.30153874],"iteration":335,"passed_time":0.3484621757,"remaining_time":0.688627633},
{"learn":[4.300480438],"iteration":336,"passed_time":0.3490624827,"remaining_time":0.6867312345},
{"learn":[4.298976405],"iteration":337,"passed_time":0.3497361364,"remaining_time":0.6849861606},
{"learn":[4.294939304],"iteration":338,"passed_time":0.350351933,"remaining_time":0.6831345949},
{"learn":[4.289582724],"iteration":339,"passed_time":0.3509593681,"remaining_time":0.6812740676},
{"learn":[4.285879319],"iteration":340,"passed_time":0.3515553734,"remaining_time":0.6793988007},
{"learn":[4.281454065],"iteration":341,"passed_time":0.3521613657,"remaining_time":0.6775502299},
{"learn":[4.277408643],"iteration":342,"passed_time":0.3527723743,"remaining_time":0.6757185128},
{"learn":[4.272638697],"iteration":343,"passed_time":0.3533841398,"remaining_time":0.6738953363},
{"learn":[4.272537515],"iteration":344,"passed_time":0.3536908435,"remaining_time":0.6715000072},
{"learn":[4.268490804],"iteration":345,"passed_time":0.3542842567,"remaining_time":0.6696586817},
{"learn":[4.264114666],"iteration":346,"passed_time":0.3549043392,"remaining_time":0.6678747362},
{"learn":[4.261681038],"iteration":347,"passed_time":0.3555200865,"remaining_time":0.6660893574},
{"learn":[4.256766403],"iteration":348,"passed_time":0.3561297693,"remaining_time":0.6642993691},
{"learn":[4.256274676],"iteration":349,"passed_time":0.35669815,"remaining_time":0.6624394215},
{"learn":[4.253983147],"iteration":350,"passed_time":0.3572902375,"remaining_time":0.660630667},
{"learn":[4.251408997],"iteration":351,"passed_time":0.3578818618,"remaining_time":0.6588279728},
{"learn":[4.246161672],"iteration":352,"passed_time":0.3584886258,"remaining_time":0.6570598892},
{"learn":[4.245022446],"iteration":353,"passed_time":0.3590953475,"remaining_time":0.6552982894},
{"learn":[4.242494379],"iteration":354,"passed_time":0.3596880627,"remaining_time":0.6535177477},
{"learn":[4.239953195],"iteration":355,"passed_time":0.3602812641,"remaining_time":0.6517447587},
{"learn":[4.236215559],"iteration":356,"passed_time":0.3608979395,"remaining_time":0.6500206585},
{"learn":[4.233732221],"iteration":357,"passed_time":0.3614946541,"remaining_time":0.6482669495},
{"learn":[4.233160413],"iteration":358,"passed_time":0.3620597431,"remaining_time":0.6464632182},
{"learn":[4.22920656],"iteration":359,"passed_time":0.3626587346,"remaining_time":0.6447266393},
{"learn":[4.224851415],"iteration":360,"passed_time":0.3632646739,"remaining_time":0.643008661},
{"learn":[4.219779541],"iteration":361,"passed_time":0.3639405039,"remaining_time":0.6414200042},
{"learn":[4.217567861],"iteration":362,"passed_time":0.3645688162,"remaining_time":0.6397529916},
{"learn":[4.21507264],"iteration":363,"passed_time":0.3651812346,"remaining_time":0.6380639154},
{"learn":[4.211221535],"iteration":364,"passed_time":0.3658003274,"remaining_time":0.6363923504},
{"learn":[4.207786699],"iteration":365,"passed_time":0.3664221155,"remaining_time":0.6347312055},
{"learn":[4.202425076],"iteration":366,"passed_time":0.3670202154,"remaining_time":0.6330348675},
{"learn":[4.2021327],"iteration":367,"passed_time":0.3675849766,"remaining_time":0.6312872424},
{"learn":[4.201123583],"iteration":368,"passed_time":0.3681773571,"remaining_time":0.6295932583},
{"learn":[4.198283797],"iteration":369,"passed_time":0.3687780718,"remaining_time":0.6279194195},
{"learn":[4.195430387],"iteration":370,"passed_time":0.3693864908,"remaining_time":0.6262644278},
{"learn":[4.194678451],"iteration":371,"passed_time":0.3699908784,"remaining_time":0.6246082571},
{"learn":[4.190767298],"iteration":372,"passed_time":0.3705905431,"remaining_time":0.6229497869},
{"learn":[4.185781877],"iteration":373,"passed_time":0.3712106256,"remaining_time":0.621331154},
{"learn":[4.18495453],"iteration":374,"passed_time":0.3718037609,"remaining_time":0.6196729348},
{"learn":[4.182247533],"iteration":375,"passed_time":0.3724040138,"remaining_time":0.6180321931},
{"learn":[4.178392266],"iteration":376,"passed_time":0.3730070735,"remaining_time":0.6164016096},
{"learn":[4.173870297],"iteration":377,"passed_time":0.3736146709,"remaining_time":0.6147839294},
{"learn":[4.170769137],"iteration":378,"passed_time":0.3742096479,"remaining_time":0.6131509006},
{"learn":[4.170072836],"iteration":379,"passed_time":0.3747977569,"remaining_time":0.6115121297},
{"learn":[4.165362979],"iteration":380,"passed_time":0.375438752,"remaining_time":0.6099647965},
{"learn":[4.160002553],"iteration":381,"passed_time":0.3760434808,"remaining_time":0.6083635371},
{"learn":[4.157515603],"iteration":382,"passed_time":0.3766602905,"remaining_time":0.6067869432},
{"learn":[4.153412292],"iteration":383,"passed_time":0.3772628162,"remaining_time":0.6051924343},
{"learn":[4.153053071],"iteration":384,"passed_time":0.3778322248,"remaining_time":0.6035501773},
{"learn":[4.149358011],"iteration":385,"passed_time":0.3784803009,"remaining_time":0.6020386134},
{"learn":[4.14387274],"iteration":386,"passed_time":0.3791276101,"remaining_time":0.6005302971},
{"learn":[4.139402304],"iteration":387,"passed_time":0.3797545202,"remaining_time":0.5989942432},
{"learn":[4.135830261],"iteration":388,"passed_time":0.3803774928,"remaining_time":0.597456679},
{"learn":[4.132882721],"iteration":389,"passed_time":0.3809862703,"remaining_time":0.5959016023},
{"learn":[4.129526949],"iteration":390,"passed_time":0.3815808764,"remaining_time":0.5943292934},
{"learn":[4.129082874],"iteration":391,"passed_time":0.3821798424,"remaining_time":0.5927687352},
{"learn":[4.127359458],"iteration":392,"passed_time":0.3827863482,"remaining_time":0.5912247159},
{"learn":[4.124081444],"iteration":393,"passed_time":0.3833948853,"remaining_time":0.58968858},
{"learn":[4.122304247],"iteration":394,"passed_time":0.3839998404,"remaining_time":0.5881516543},
{"learn":[4.118378443],"iteration":395,"passed_time":0.3846122726,"remaining_time":0.58663084},
{"learn":[4.118097315],"iteration":396,"passed_time":0.3851702162,"remaining_time":0.5850318397},
{"learn":[4.115241653],"iteration":397,"passed_time":0.3857634861,"remaining_time":0.5834915042},
{"learn":[4.11122408],"iteration":398,"passed_time":0.3863717213,"remaining_time":0.5819784574},
{"learn":[4.107951407],"iteration":399,"passed_time":0.3869625745,"remaining_time":0.5804438618},
{"learn":[4.106091265],"iteration":400,"passed_time":0.3875667245,"remaining_time":0.5789338354},
{"learn":[4.102955713],"iteration":401,"passed_time":0.3881866007,"remaining_time":0.5774517095},
{"learn":[4.10166257],"iteration":402,"passed_time":0.3887893292,"remaining_time":0.5759484604},
{"learn":[4.097105714],"iteration":403,"passed_time":0.3893855152,"remaining_time":0.5744400175},
{"learn":[4.096260725],"iteration":404,"passed_time":0.3900141887,"remaining_time":0.5729838081},
{"learn":[4.092038656],"iteration":405,"passed_time":0.3906221194,"remaining_time":0.5715013275},
{"learn":[4.089518859],"iteration":406,"passed_time":0.3912295705,"remaining_time":0.5700224454},
{"learn":[4.086665574],"iteration":407,"passed_time":0.3918186982,"remaining_time":0.5685212483},
{"learn":[4.082929757],"iteration":408,"passed_time":0.392420971,"remaining_time":0.5670435058},
{"learn":[4.079031074],"iteration":409,"passed_time":0.3930546071,"remaining_time":0.5656151664},
{"learn":[4.075863087],"iteration":410,"passed_time":0.3936951383,"remaining_time":0.5642005753},
{"learn":[4.072979972],"iteration":411,"passed_time":0.394304329,"remaining_time":0.5627450133},
{"learn":[4.069374843],"iteration":412,"passed_time":0.3948832627,"remaining_time":0.5612505452},
{"learn":[4.065697587],"iteration":413,"passed_time":0.3954902488,"remaining_time":0.5598002072},
{"learn":[4.064265525],"iteration":414,"passed_time":0.3960859117,"remaining_time":0.5583379719},
{"learn":[4.063438567],"iteration":415,"passed_time":0.3966922112,"remaining_time":0.556894835},
{"learn":[4.060466252],"iteration":416,"passed_time":0.3973033186,"remaining_time":0.5554624335},
{"learn":[4.056980925],"iteration":417,"passed_time":0.3979076536,"remaining_time":0.554024532},
{"learn":[4.05195143],"iteration":418,"passed_time":0.398525829,"remaining_time":0.552609801},
{"learn":[4.049830702],"iteration":419,"passed_time":0.3991210935,"remaining_time":0.5511672243},
{"learn":[4.047332808],"iteration":420,"passed_time":0.3997222262,"remaining_time":0.5497367434},
{"learn":[4.043800796],"iteration":421,"passed_time":0.4003113835,"remaining_time":0.5482937906},
{"learn":[4.039812873],"iteration":422,"passed_time":0.4008977787,"remaining_time":0.5468511071},
{"learn":[4.035004594],"iteration":423,"passed_time":0.401516047,"remaining_time":0.545455762},
{"learn":[4.031551745],"iteration":424,"passed_time":0.4021149132,"remaining_time":0.5440378237},
{"learn":[4.028861075],"iteration":425,"passed_time":0.4027160239,"remaining_time":0.5426267552},
{"learn":[4.023858613],"iteration":426,"passed_time":0.4033119836,"remaining_time":0.5412125682},
{"learn":[4.020294015],"iteration":427,"passed_time":0.4039340355,"remaining_time":0.5398370755},
{"learn":[4.020044769],"iteration":428,"passed_time":0.4045131489,"remaining_time":0.5384079441},
{"learn":[4.019829041],"iteration":429,"passed_time":0.4050945209,"remaining_time":0.5369857602},
{"learn":[4.017279066],"iteration":430,"passed_time":0.4057085698,"remaining_time":0.5356106177},
{"learn":[4.016220097],"iteration":431,"passed_time":0.4062966996,"remaining_time":0.5342049198},
{"learn":[4.015391783],"iteration":432,"passed_time":0.406944933,"remaining_time":0.5328817021},
{"learn":[4.015048356],"iteration":433,"passed_time":0.4075610822,"remaining_time":0.5315197524},
{"learn":[4.01079293],"iteration":434,"passed_time":0.408173814,"remaining_time":0.5301567929},
{"learn":[4.007733078],"iteration":435,"passed_time":0.4087949357,"remaining_time":0.5288081278},
{"learn":[4.004747521],"iteration":436,"passed_time":0.4094180688,"remaining_time":0.5274653839},
{"learn":[4.001404764],"iteration":437,"passed_time":0.410036902,"remaining_time":0.5261204085},
{"learn":[3.999119835],"iteration":438,"passed_time":0.4106379131,"remaining_time":0.5247559664},
{"learn":[3.998388187],"iteration":439,"passed_time":0.411224456,"remaining_time":0.5233765804},
{"learn":[3.996239716],"iteration":440,"passed_time":0.4118172976,"remaining_time":0.5220087741},
{"learn":[3.992240427],"iteration":441,"passed_time":0.4124182193,"remaining_time":0.520654675},
{"learn":[3.987741798],"iteration":442,"passed_time":0.4130307744,"remaining_time":0.5193186035},
{"learn":[3.983618605],"iteration":443,"passed_time":0.413622752,"remaining_time":0.5179600228},
{"learn":[3.980116082],"iteration":444,"passed_time":0.4142266148,"remaining_time":0.5166197106},
{"learn":[3.978842957],"iteration":445,"passed_time":0.4148459827,"remaining_time":0.5153019606},
{"learn":[3.977063396],"iteration":446,"passed_time":0.4154408164,"remaining_time":0.5139569832},
{"learn":[3.975690074],"iteration":447,"passed_time":0.4160372228,"remaining_time":0.5126172924},
{"learn":[3.974918079],"iteration":448,"passed_time":0.4166353689,"remaining_time":0.5112830474},
{"learn":[3.97376044],"iteration":449,"passed_time":0.4172320959,"remaining_time":0.5099503394},
{"learn":[3.970750177],"iteration":450,"passed_time":0.4178384302,"remaining_time":0.5086325902},
{"learn":[3.96910051],"iteration":451,"passed_time":0.4184415574,"remaining_time":0.5073141006},
{"learn":[3.965943683],"iteration":452,"passed_time":0.419020125,"remaining_time":0.5059691134},
{"learn":[3.962292254],"iteration":453,"passed_time":0.4196129869,"remaining_time":0.5046446935},
{"learn":[3.96198446],"iteration":454,"passed_time":0.4202084676,"remaining_time":0.5033266261},
{"learn":[3.959847452],"iteration":455,"passed_time":0.4208223819,"remaining_time":0.5020337188},
{"learn":[3.957237729],"iteration":456,"passed_time":0.4215191259,"remaining_time":0.5008422},
{"learn":[3.957079337],"iteration":457,"passed_time":0.4221333543,"remaining_time":0.4995551922},
{"learn":[3.954571029],"iteration":458,"passed_time":0.4227714306,"remaining_time":0.4982992242},
{"learn":[3.951308203],"iteration":459,"passed_time":0.4233847064,"remaining_time":0.4970168293},
{"learn":[3.948007051],"iteration":460,"passed_time":0.424002586,"remaining_time":0.4957427199},
{"learn":[3.946087076],"iteration":461,"passed_time":0.4246119875,"remaining_time":0.4944615785},
{"learn":[3.944079261],"iteration":462,"passed_time":0.4252638556,"remaining_time":0.4932325928},
{"learn":[3.940389465],"iteration":463,"passed_time":0.4258765878,"remaining_time":0.4919608859},
{"learn":[3.939754337],"iteration":464,"passed_time":0.4264742848,"remaining_time":0.4906747148},
{"learn":[3.936239721],"iteration":465,"passed_time":0.4271183815,"remaining_time":0.4894446689},
{"learn":[3.935844729],"iteration":466,"passed_time":0.4277048972,"remaining_time":0.4881514137},
{"learn":[3.934771856],"iteration":467,"passed_time":0.4282845788,"remaining_time":0.4868534101},
{"learn":[3.931155375],"iteration":468,"passed_time":0.428885747,"remaining_time":0.4855827967},
{"learn":[3.928451757],"iteration":469,"passed_time":0.4294901797,"remaining_time":0.4843187133},
{"learn":[3.924604823],"iteration":470,"passed_time":0.4300896254,"remaining_time":0.4830518298},
{"learn":[3.92064939],"iteration":471,"passed_time":0.430696054,"remaining_time":0.4817955858},
{"learn":[3.920047658],"iteration":472,"passed_time":0.4313069834,"remaining_time":0.4805471041},
{"learn":[3.916797938],"iteration":473,"passed_time":0.4319140226,"remaining_time":0.4792969955},
{"learn":[3.915221213],"iteration":474,"passed_time":0.4325007043,"remaining_time":0.4780270942},
{"learn":[3.912449046],"iteration":475,"passed_time":0.4331148665,"remaining_time":0.4767903152},
{"learn":[3.910335839],"iteration":476,"passed_time":0.4337217139,"remaining_time":0.4755481265},
{"learn":[3.908348883],"iteration":477,"passed_time":0.4343352649,"remaining_time":0.4743159169},
{"learn":[3.906547461],"iteration":478,"passed_time":0.4349481619,"remaining_time":0.4730855791},
{"learn":[3.904619761],"iteration":479,"passed_time":0.4355444995,"remaining_time":0.4718398744},
{"learn":[3.902855068],"iteration":480,"passed_time":0.4361608184,"remaining_time":0.4706184298},
{"learn":[3.899335227],"iteration":481,"passed_time":0.4368053803,"remaining_time":0.4694298486},
{"learn":[3.894826272],"iteration":482,"passed_time":0.4374252414,"remaining_time":0.4682170803},
{"learn":[3.892254528],"iteration":483,"passed_time":0.4380469874,"remaining_time":0.4670087717},
{"learn":[3.888516774],"iteration":484,"passed_time":0.4386678378,"remaining_time":0.4658019308},
{"learn":[3.888264413],"iteration":485,"passed_time":0.4392418164,"remaining_time":0.4645479293},
{"learn":[3.884094922],"iteration":486,"passed_time":0.4398718584,"remaining_time":0.4633557769},
{"learn":[3.880543496],"iteration":487,"passed_time":0.4405059897,"remaining_time":0.4621702187},
{"learn":[3.878700673],"iteration":488,"passed_time":0.4411266617,"remaining_time":0.460972851},
{"learn":[3.878198529],"iteration":489,"passed_time":0.4417205109,"remaining_time":0.4597499195},
{"learn":[3.876406458],"iteration":490,"passed_time":0.4423791285,"remaining_time":0.4585966933},
{"learn":[3.874115067],"iteration":491,"passed_time":0.4430061694,"remaining_time":0.4574128741},
{"learn":[3.873116881],"iteration":492,"passed_time":0.4436239543,"remaining_time":0.4562217948},
{"learn":[3.871423684],"iteration":493,"passed_time":0.4442433219,"remaining_time":0.4550346576},
{"learn":[3.869363076],"iteration":494,"passed_time":0.4448385561,"remaining_time":0.4538251936},
{"learn":[3.866402298],"iteration":495,"passed_time":0.4454428077,"remaining_time":0.4526273691},
{"learn":[3.86453055],"iteration":496,"passed_time":0.4460713638,"remaining_time":0.4514565311},
{"learn":[3.862076452],"iteration":497,"passed_time":0.4466924803,"remaining_time":0.4502803717},
{"learn":[3.858488545],"iteration":498,"passed_time":0.4472994055,"remaining_time":0.4490921887},
{"learn":[3.855823349],"iteration":499,"passed_time":0.4480359226,"remaining_time":0.4480359226},
{"learn":[3.854517284],"iteration":500,"passed_time":0.4486257487,"remaining_time":0.4468348275},
{"learn":[3.851991495],"iteration":501,"passed_time":0.4493016631,"remaining_time":0.4457215702},
{"learn":[3.850087836],"iteration":502,"passed_time":0.4499363143,"remaining_time":0.4445692808},
{"learn":[3.84978811],"iteration":503,"passed_time":0.4506124905,"remaining_time":0.4434599113},
{"learn":[3.846669885],"iteration":504,"passed_time":0.4513284259,"remaining_time":0.4423912294},
{"learn":[3.845719823],"iteration":505,"passed_time":0.4519497216,"remaining_time":0.4412315464},
{"learn":[3.842015137],"iteration":506,"passed_time":0.4525857093,"remaining_time":0.4400882735},
{"learn":[3.83885039],"iteration":507,"passed_time":0.4532710781,"remaining_time":0.4389948237},
{"learn":[3.834943165],"iteration":508,"passed_time":0.4539255534,"remaining_time":0.4378731763},
{"learn":[3.834085207],"iteration":509,"passed_time":0.4545409081,"remaining_time":0.4367157745},
{"learn":[3.830361355],"iteration":510,"passed_time":0.4551777437,"remaining_time":0.4355810502},
{"learn":[3.828303719],"iteration":511,"passed_time":0.4558042835,"remaining_time":0.4344384578},
{"learn":[3.825125071],"iteration":512,"passed_time":0.4564957506,"remaining_time":0.4333595137},
{"learn":[3.821456005],"iteration":513,"passed_time":0.4571283378,"remaining_time":0.432226405},
{"learn":[3.819436391],"iteration":514,"passed_time":0.4577486799,"remaining_time":0.4310837082},
{"learn":[3.817687992],"iteration":515,"passed_time":0.4584492311,"remaining_time":0.430018271},
{"learn":[3.816208052],"iteration":516,"passed_time":0.4590773588,"remaining_time":0.4288865847},
{"learn":[3.813173643],"iteration":517,"passed_time":0.4597022372,"remaining_time":0.4277538191},
{"learn":[3.811903481],"iteration":518,"passed_time":0.4603522186,"remaining_time":0.4266462758},
{"learn":[3.811682943],"iteration":519,"passed_time":0.4609789651,"remaining_time":0.4255190447},
{"learn":[3.808059675],"iteration":520,"passed_time":0.4616010648,"remaining_time":0.4243894626},
{"learn":[3.80436121],"iteration":521,"passed_time":0.4622175174,"remaining_time":0.4232566538},
{"learn":[3.802429147],"iteration":522,"passed_time":0.4628326865,"remaining_time":0.4221246491},
{"learn":[3.800367982],"iteration":523,"passed_time":0.463461142,"remaining_time":0.4210066863},
{"learn":[3.796461609],"iteration":524,"passed_time":0.464140508,"remaining_time":0.4199366501},
{"learn":[3.793320827],"iteration":525,"passed_time":0.4648179775,"remaining_time":0.4188663904},
{"learn":[3.79304187],"iteration":526,"passed_time":0.4654544738,"remaining_time":0.4177608465},
{"learn":[3.790155154],"iteration":527,"passed_time":0.4660836767,"remaining_time":0.4166505594},
{"learn":[3.788243159],"iteration":528,"passed_time":0.4666957493,"remaining_time":0.4155268392},
{"learn":[3.786206993],"iteration":529,"passed_time":0.4673346668,"remaining_time":0.4144288555},
{"learn":[3.783232143],"iteration":530,"passed_time":0.4679615318,"remaining_time":0.4133219556},
{"learn":[3.779962539],"iteration":531,"passed_time":0.4685908386,"remaining_time":0.4122190084},
{"learn":[3.775618896],"iteration":532,"passed_time":0.4692587966,"remaining_time":0.4111517036},
{"learn":[3.773949432],"iteration":533,"passed_time":0.4698990912,"remaining_time":0.4100617537},
{"learn":[3.772032999],"iteration":534,"passed_time":0.4705329239,"remaining_time":0.4089678684},
{"learn":[3.769326406],"iteration":535,"passed_time":0.4711788977,"remaining_time":0.4078862099},
{"learn":[3.768527925],"iteration":536,"passed_time":0.4718097727,"remaining_time":0.406793156},
{"learn":[3.764941978],"iteration":537,"passed_time":0.4724448658,"remaining_time":0.4057054423},
{"learn":[3.763214032],"iteration":538,"passed_time":0.4731029837,"remaining_time":0.4046391011},
{"learn":[3.76234982],"iteration":539,"passed_time":0.4737430245,"remaining_time":0.4035588727},
{"learn":[3.761581965],"iteration":540,"passed_time":0.4743600935,"remaining_time":0.4024607817},
{"learn":[3.757534386],"iteration":541,"passed_time":0.475012077,"remaining_time":0.4013939691},
{"learn":[3.756290537],"iteration":542,"passed_time":0.4756541744,"remaining_time":0.400320364},
{"learn":[3.752854848],"iteration":543,"passed_time":0.4762811929,"remaining_time":0.3992357058},
{"learn":[3.752010551],"iteration":544,"passed_time":0.4769189031,"remaining_time":0.398161653},
{"learn":[3.750500811],"iteration":545,"passed_time":0.4775473287,"remaining_time":0.3970814784},
{"learn":[3.748249454],"iteration":546,"passed_time":0.4781728024,"remaining_time":0.396000511},
{"learn":[3.74571225],"iteration":547,"passed_time":0.478796719,"remaining_time":0.3949199215},
{"learn":[3.745200052],"iteration":548,"passed_time":0.4794714481,"remaining_time":0.3938827379},
{"learn":[3.742660443],"iteration":549,"passed_time":0.480142527,"remaining_time":0.3928438857},
{"learn":[3.739635149],"iteration":550,"passed_time":0.4808268445,"remaining_time":0.3918171564},
{"learn":[3.739075308],"iteration":551,"passed_time":0.4814597175,"remaining_time":0.3907499156},
{"learn":[3.735762476],"iteration":552,"passed_time":0.4821011691,"remaining_time":0.3896911801},
{"learn":[3.733627321],"iteration":553,"passed_time":0.4827409055,"remaining_time":0.3886325702},
{"learn":[3.732836753],"iteration":554,"passed_time":0.4833502949,"remaining_time":0.3875511374},
{"learn":[3.732077684],"iteration":555,"passed_time":0.4839867107,"remaining_time":0.3864929848},
{"learn":[3.7302797],"iteration":556,"passed_time":0.4845943449,"remaining_time":0.3854134557},
{"learn":[3.727753432],"iteration":557,"passed_time":0.4852252602,"remaining_time":0.3843540592},
{"learn":[3.725317377],"iteration":558,"passed_time":0.4858855328,"remaining_time":0.3833193559},
{"learn":[3.723047838],"iteration":559,"passed_time":0.4865393366,"remaining_time":0.3822809074},
{"learn":[3.722511701],"iteration":560,"passed_time":0.4871710333,"remaining_time":0.3812265305},
{"learn":[3.721894572],"iteration":561,"passed_time":0.4877839806,"remaining_time":0.3801590454},
{"learn":[3.719343308],"iteration":562,"passed_time":0.4884487347,"remaining_time":0.3791333873},
{"learn":[3.715486325],"iteration":563,"passed_time":0.4890920314,"remaining_time":0.3780924215},
{"learn":[3.715169409],"iteration":564,"passed_time":0.4896764624,"remaining_time":0.3770075418},
{"learn":[3.712321827],"iteration":565,"passed_time":0.4903137539,"remaining_time":0.3759649632},
{"learn":[3.709759327],"iteration":566,"passed_time":0.4909361597,"remaining_time":0.3749124465},
{"learn":[3.705826322],"iteration":567,"passed_time":0.4916107638,"remaining_time":0.3739011443},
{"learn":[3.702513551],"iteration":568,"passed_time":0.4922516645,"remaining_time":0.3728654963},
{"learn":[3.701577703],"iteration":569,"passed_time":0.4928701071,"remaining_time":0.3718142913},
{"learn":[3.699818174],"iteration":570,"passed_time":0.49351798,"remaining_time":0.3707867136},
{"learn":[3.698686873],"iteration":571,"passed_time":0.4941853168,"remaining_time":0.3697750273},
{"learn":[3.696255243],"iteration":572,"passed_time":0.4948433693,"remaining_time":0.3687576243},
{"learn":[3.69517553],"iteration":573,"passed_time":0.4954780599,"remaining_time":0.367724135},
{"learn":[3.692692359],"iteration":574,"passed_time":0.4961315055,"remaining_time":0.3667058954},
{"learn":[3.690279725],"iteration":575,"passed_time":0.496740721,"remaining_time":0.3656563641},
{"learn":[3.688806385],"iteration":576,"passed_time":0.4974808904,"remaining_time":0.3647043616},
{"learn":[3.687936864],"iteration":577,"passed_time":0.4981765401,"remaining_time":0.3637205881},
{"learn":[3.686668712],"iteration":578,"passed_time":0.4988105532,"remaining_time":0.3626929929},
{"learn":[3.683155292],"iteration":579,"passed_time":0.4994134346,"remaining_time":0.3616442113},
{"learn":[3.68261471],"iteration":580,"passed_time":0.5000557909,"remaining_time":0.3606254327},
{"learn":[3.678847961],"iteration":581,"passed_time":0.5006872658,"remaining_time":0.3596001325},
{"learn":[3.678151708],"iteration":582,"passed_time":0.5012976618,"remaining_time":0.3585611063},
{"learn":[3.677718019],"iteration":583,"passed_time":0.5019874718,"remaining_time":0.3575801169},
{"learn":[3.675361127],"iteration":584,"passed_time":0.5026459079,"remaining_time":0.3565778663},
{"learn":[3.672351857],"iteration":585,"passed_time":0.5032902687,"remaining_time":0.3555668451},
{"learn":[3.669090143],"iteration":586,"passed_time":0.5039172208,"remaining_time":0.3545448248},
{"learn":[3.667659402],"iteration":587,"passed_time":0.5045844436,"remaining_time":0.3535523652},
{"learn":[3.664629641],"iteration":588,"passed_time":0.505217872,"remaining_time":0.3525374285},
{"learn":[3.662036709],"iteration":589,"passed_time":0.5058679464,"remaining_time":0.3515353526},
{"learn":[3.659465979],"iteration":590,"passed_time":0.5065012299,"remaining_time":0.3505228477},
{"learn":[3.65670228],"iteration":591,"passed_time":0.5072435928,"remaining_time":0.3495868005},
{"learn":[3.653687649],"iteration":592,"passed_time":0.5079221492,"remaining_time":0.3486076133},
{"learn":[3.650229712],"iteration":593,"passed_time":0.5085825023,"remaining_time":0.3476169965},
{"learn":[3.647404873],"iteration":594,"passed_time":0.5092223586,"remaining_time":0.3466135382},
{"learn":[3.643067645],"iteration":595,"passed_time":0.5098594086,"remaining_time":0.3456093978},
{"learn":[3.641326388],"iteration":596,"passed_time":0.5104714283,"remaining_time":0.3445895906},
{"learn":[3.639690015],"iteration":597,"passed_time":0.5111159237,"remaining_time":0.3435929788},
{"learn":[3.637328334],"iteration":598,"passed_time":0.5117383833,"remaining_time":0.3425827908},
{"learn":[3.635149564],"iteration":599,"passed_time":0.5123732556,"remaining_time":0.3415821704},
{"learn":[3.631333359],"iteration":600,"passed_time":0.5130025683,"remaining_time":0.3405790761},
{"learn":[3.631109832],"iteration":601,"passed_time":0.5135953017,"remaining_time":0.33955304},
{"learn":[3.628481917],"iteration":602,"passed_time":0.5142156187,"remaining_time":0.3385466014},
{"learn":[3.624896441],"iteration":603,"passed_time":0.5148537535,"remaining_time":0.3375531231},
{"learn":[3.624757999],"iteration":604,"passed_time":0.5154779497,"remaining_time":0.3365517192},
{"learn":[3.624200841],"iteration":605,"passed_time":0.5160784842,"remaining_time":0.3355361762},
{"learn":[3.620926042],"iteration":606,"passed_time":0.5167038175,"remaining_time":0.3345380564},
{"learn":[3.617000033],"iteration":607,"passed_time":0.51731854,"remaining_time":0.3335343218},
{"learn":[3.616419007],"iteration":608,"passed_time":0.5179935267,"remaining_time":0.3325705565},
{"learn":[3.614495054],"iteration":609,"passed_time":0.5186323247,"remaining_time":0.331584601},
{"learn":[3.611333455],"iteration":610,"passed_time":0.5193406516,"remaining_time":0.3306440482},
{"learn":[3.609169374],"iteration":611,"passed_time":0.5200154844,"remaining_time":0.3296830195},
{"learn":[3.608585858],"iteration":612,"passed_time":0.5206519907,"remaining_time":0.3286987282},
{"learn":[3.606114601],"iteration":613,"passed_time":0.5212528025,"remaining_time":0.3276931299},
{"learn":[3.604731529],"iteration":614,"passed_time":0.5219542349,"remaining_time":0.3267518381},
{"learn":[3.602609512],"iteration":615,"passed_time":0.5226166312,"remaining_time":0.3257869909},
{"learn":[3.599376176],"iteration":616,"passed_time":0.5233263124,"remaining_time":0.3248524759},
{"learn":[3.595778988],"iteration":617,"passed_time":0.5239580817,"remaining_time":0.3238705295},
{"learn":[3.595181434],"iteration":618,"passed_time":0.5246213537,"remaining_time":0.3229091046},
{"learn":[3.592978539],"iteration":619,"passed_time":0.5252608566,"remaining_time":0.3219340734},
{"learn":[3.58998066],"iteration":620,"passed_time":0.5258919517,"remaining_time":0.3209549914},
{"learn":[3.589579428],"iteration":621,"passed_time":0.5264996152,"remaining_time":0.3199627886},
{"learn":[3.587229716],"iteration":622,"passed_time":0.5271754486,"remaining_time":0.3190130725},
{"learn":[3.585565911],"iteration":623,"passed_time":0.5278047623,"remaining_time":0.3180362029},
{"learn":[3.582091528],"iteration":624,"passed_time":0.5284320295,"remaining_time":0.3170592177},
{"learn":[3.579430272],"iteration":625,"passed_time":0.529103449,"remaining_time":0.3161097283},
{"learn":[3.577570312],"iteration":626,"passed_time":0.5297485171,"remaining_time":0.3151454496},
{"learn":[3.577408311],"iteration":627,"passed_time":0.5303528062,"remaining_time":0.3141580317},
{"learn":[3.57448581],"iteration":628,"passed_time":0.5310133908,"remaining_time":0.3132050366},
{"learn":[3.572539898],"iteration":629,"passed_time":0.5316364874,"remaining_time":0.3122309529},
{"learn":[3.572213124],"iteration":630,"passed_time":0.5322592614,"remaining_time":0.3112577931},
{"learn":[3.569387463],"iteration":631,"passed_time":0.5328897731,"remaining_time":0.3102902476},
{"learn":[3.566997683],"iteration":632,"passed_time":0.5335215473,"remaining_time":0.309324499},
{"learn":[3.564715346],"iteration":633,"passed_time":0.5341521633,"remaining_time":0.3083591353},
{"learn":[3.562541882],"iteration":634,"passed_time":0.5347554593,"remaining_time":0.3073791223},
{"learn":[3.561338001],"iteration":635,"passed_time":0.535447562,"remaining_time":0.3064511204},
{"learn":[3.55940532],"iteration":636,"passed_time":0.5361720231,"remaining_time":0.3055422989},
{"learn":[3.558563829],"iteration":637,"passed_time":0.5368492286,"remaining_time":0.3046072425},
{"learn":[3.555544273],"iteration":638,"passed_time":0.5374759306,"remaining_time":0.3036444616},
{"learn":[3.555290993],"iteration":639,"passed_time":0.5381018138,"remaining_time":0.3026822703},
{"learn":[3.553600085],"iteration":640,"passed_time":0.538726342,"remaining_time":0.3017203694},
{"learn":[3.549578378],"iteration":641,"passed_time":0.5393914793,"remaining_time":0.3007821645},
{"learn":[3.549470915],"iteration":642,"passed_time":0.5401117017,"remaining_time":0.2998753927},
{"learn":[3.546795972],"iteration":643,"passed_time":0.5409019178,"remaining_time":0.2990078925},
{"learn":[3.54531422],"iteration":644,"passed_time":0.5416478821,"remaining_time":0.2981162762},
{"learn":[3.543448475],"iteration":645,"passed_time":0.5423574693,"remaining_time":0.2972051767},
{"learn":[3.542045775],"iteration":646,"passed_time":0.5429837458,"remaining_time":0.2962492461},
{"learn":[3.540847741],"iteration":647,"passed_time":0.5436195916,"remaining_time":0.2952995312},
{"learn":[3.540587216],"iteration":648,"passed_time":0.5442902205,"remaining_time":0.2943695953},
{"learn":[3.538485721],"iteration":649,"passed_time":0.5449234822,"remaining_time":0.2934203366},
{"learn":[3.534916752],"iteration":650,"passed_time":0.5455488161,"remaining_time":0.2924677985},
{"learn":[3.531610653],"iteration":651,"passed_time":0.5462652206,"remaining_time":0.2915648724},
{"learn":[3.528018222],"iteration":652,"passed_time":0.547081294,"remaining_time":0.2907154809},
{"learn":[3.525680528],"iteration":653,"passed_time":0.5477523092,"remaining_time":0.289789448},
{"learn":[3.522824261],"iteration":654,"passed_time":0.5483771672,"remaining_time":0.288839882},
{"learn":[3.519566063],"iteration":655,"passed_time":0.5490057729,"remaining_time":0.2878932712},
{"learn":[3.51823992],"iteration":656,"passed_time":0.5496643837,"remaining_time":0.2869632931},
{"learn":[3.51629373],"iteration":657,"passed_time":0.5502949236,"remaining_time":0.28601955},
{"learn":[3.516045954],"iteration":658,"passed_time":0.5510385948,"remaining_time":0.2851352972},
{"learn":[3.514100246],"iteration":659,"passed_time":0.5518148644,"remaining_time":0.2842682635},
{"learn":[3.511091082],"iteration":660,"passed_time":0.5526283998,"remaining_time":0.2834206165},
{"learn":[3.508005493],"iteration":661,"passed_time":0.5532914669,"remaining_time":0.2824962474},
{"learn":[3.507410268],"iteration":662,"passed_time":0.5539222954,"remaining_time":0.2815562799},
{"learn":[3.50473836],"iteration":663,"passed_time":0.5545461861,"remaining_time":0.2806137327},
{"learn":[3.503334362],"iteration":664,"passed_time":0.5552026718,"remaining_time":0.279688564},
{"learn":[3.500251794],"iteration":665,"passed_time":0.5558427261,"remaining_time":0.2787559617},
{"learn":[3.499474575],"iteration":666,"passed_time":0.5564961297,"remaining_time":0.2778309013},
{"learn":[3.49648521],"iteration":667,"passed_time":0.5572192127,"remaining_time":0.2769412854},
{"learn":[3.492748732],"iteration":668,"passed_time":0.5579899598,"remaining_time":0.2760757499},
{"learn":[3.490757242],"iteration":669,"passed_time":0.5586151329,"remaining_time":0.2751387968},
{"learn":[3.490403809],"iteration":670,"passed_time":0.5592150866,"remaining_time":0.2741904076},
{"learn":[3.489261805],"iteration":671,"passed_time":0.5599093932,"remaining_time":0.2732891086},
{"learn":[3.488714915],"iteration":672,"passed_time":0.5605381118,"remaining_time":0.2723565566},
{"learn":[3.488327473],"iteration":673,"passed_time":0.5611787239,"remaining_time":0.2714306588},
{"learn":[3.484795631],"iteration":674,"passed_time":0.561833305,"remaining_time":0.270512332},
{"learn":[3.481545715],"iteration":675,"passed_time":0.5626148309,"remaining_time":0.269655629},
{"learn":[3.480383634],"iteration":676,"passed_time":0.5634580445,"remaining_time":0.2688285796},
{"learn":[3.477845631],"iteration":677,"passed_time":0.5642317862,"remaining_time":0.2679684884},
{"learn":[3.476707222],"iteration":678,"passed_time":0.5649860357,"remaining_time":0.2670994366},
{"learn":[3.473872193],"iteration":679,"passed_time":0.5656546642,"remaining_time":0.2661904302},
{"learn":[3.473430873],"iteration":680,"passed_time":0.5662884532,"remaining_time":0.2652658099},
{"learn":[3.470966498],"iteration":681,"passed_time":0.5669313642,"remaining_time":0.2643462959},
{"learn":[3.470349352],"iteration":682,"passed_time":0.5675638829,"remaining_time":0.2634227685},
{"learn":[3.467550747],"iteration":683,"passed_time":0.56824005,"remaining_time":0.262520257},
{"learn":[3.465037653],"iteration":684,"passed_time":0.5689299213,"remaining_time":0.2616247083},
{"learn":[3.462814936],"iteration":685,"passed_time":0.5697517048,"remaining_time":0.2607901389},
{"learn":[3.4608747],"iteration":686,"passed_time":0.5705555187,"remaining_time":0.2599474197},
{"learn":[3.458433177],"iteration":687,"passed_time":0.5712556477,"remaining_time":0.2590577937},
{"learn":[3.457688817],"iteration":688,"passed_time":0.5720036513,"remaining_time":0.2581903274},
{"learn":[3.455360245],"iteration":689,"passed_time":0.572662345,"remaining_time":0.2572830825},
{"learn":[3.452704958],"iteration":690,"passed_time":0.5733937546,"remaining_time":0.256409074},
{"learn":[3.449507782],"iteration":691,"passed_time":0.5743511997,"remaining_time":0.2556360831},
{"learn":[3.447844411],"iteration":692,"passed_time":0.5751726867,"remaining_time":0.2548023302},
{"learn":[3.444963599],"iteration":693,"passed_time":0.5758361095,"remaining_time":0.2538989186},
{"learn":[3.44033591],"iteration":694,"passed_time":0.5764798949,"remaining_time":0.2529875798},
{"learn":[3.4388155],"iteration":695,"passed_time":0.5771108908,"remaining_time":0.2520714236},
{"learn":[3.437589582],"iteration":696,"passed_time":0.5777644746,"remaining_time":0.251165905},
{"learn":[3.436857868],"iteration":697,"passed_time":0.5783966719,"remaining_time":0.2502518552},
{"learn":[3.434680826],"iteration":698,"passed_time":0.5790715756,"remaining_time":0.2493570018},
{"learn":[3.434354714],"iteration":699,"passed_time":0.5802005784,"remaining_time":0.2486573907},
{"learn":[3.431411043],"iteration":700,"passed_time":0.5810381387,"remaining_time":0.2478322446},
{"learn":[3.42900853],"iteration":701,"passed_time":0.5817600436,"remaining_time":0.2469579672},
{"learn":[3.427594287],"iteration":702,"passed_time":0.5827004616,"remaining_time":0.2461764397},
{"learn":[3.427371093],"iteration":703,"passed_time":0.5834125688,"remaining_time":0.2452984664},
{"learn":[3.426435864],"iteration":704,"passed_time":0.5840784762,"remaining_time":0.2444016319},
{"learn":[3.424978672],"iteration":705,"passed_time":0.5847456197,"remaining_time":0.2435059663},
{"learn":[3.421824554],"iteration":706,"passed_time":0.5853873125,"remaining_time":0.2426003996},
{"learn":[3.419898478],"iteration":707,"passed_time":0.5860740873,"remaining_time":0.2417141716},
{"learn":[3.417325277],"iteration":708,"passed_time":0.5867333578,"remaining_time":0.2408172174},
{"learn":[3.415924849],"iteration":709,"passed_time":0.5873752371,"remaining_time":0.2399138292},
{"learn":[3.412903693],"iteration":710,"passed_time":0.5880137259,"remaining_time":0.2390097986},
{"learn":[3.410554541],"iteration":711,"passed_time":0.5886674464,"remaining_time":0.2381126749},
{"learn":[3.408721136],"iteration":712,"passed_time":0.5892925413,"remaining_time":0.2372047116},
{"learn":[3.407543506],"iteration":713,"passed_time":0.5899917785,"remaining_time":0.236327239},
{"learn":[3.406075692],"iteration":714,"passed_time":0.590679053,"remaining_time":0.2354454966},
{"learn":[3.405667844],"iteration":715,"passed_time":0.5913582026,"remaining_time":0.2345610748},
{"learn":[3.402635834],"iteration":716,"passed_time":0.5920439799,"remaining_time":0.2336798414},
{"learn":[3.40075923],"iteration":717,"passed_time":0.5927183584,"remaining_time":0.2327946756},
{"learn":[3.398948077],"iteration":718,"passed_time":0.593349063,"remaining_time":0.2318930274},
{"learn":[3.395921161],"iteration":719,"passed_time":0.5941568872,"remaining_time":0.2310610117},
{"learn":[3.392029773],"iteration":720,"passed_time":0.5948870592,"remaining_time":0.2301990146},
{"learn":[3.39182118],"iteration":721,"passed_time":0.5956531671,"remaining_time":0.2293512195},
{"learn":[3.391243191],"iteration":722,"passed_time":0.5963416888,"remaining_time":0.228473925},
{"learn":[3.388856347],"iteration":723,"passed_time":0.5970386567,"remaining_time":0.2276003719},
{"learn":[3.387386151],"iteration":724,"passed_time":0.5977630933,"remaining_time":0.2267377251},
{"learn":[3.384612103],"iteration":725,"passed_time":0.5983926467,"remaining_time":0.225839649},
{"learn":[3.382440348],"iteration":726,"passed_time":0.5990206666,"remaining_time":0.2249417359},
{"learn":[3.379390582],"iteration":727,"passed_time":0.5996892469,"remaining_time":0.2240597186},
{"learn":[3.375531921],"iteration":728,"passed_time":0.6003335326,"remaining_time":0.2231692556},
{"learn":[3.374002175],"iteration":729,"passed_time":0.6010056966,"remaining_time":0.2222897782},
{"learn":[3.372481724],"iteration":730,"passed_time":0.6019033555,"remaining_time":0.2214938476},
{"learn":[3.370448601],"iteration":731,"passed_time":0.6025563163,"remaining_time":0.2206080502},
{"learn":[3.369802019],"iteration":732,"passed_time":0.6032215322,"remaining_time":0.2197273521},
{"learn":[3.368827244],"iteration":733,"passed_time":0.6038899014,"remaining_time":0.2188483839},
{"learn":[3.367516321],"iteration":734,"passed_time":0.6045385078,"remaining_time":0.2179628633},
{"learn":[3.366674714],"iteration":735,"passed_time":0.6052765897,"remaining_time":0.2171100811},
{"learn":[3.366161081],"iteration":736,"passed_time":0.6059529342,"remaining_time":0.216235579},
{"learn":[3.365745046],"iteration":737,"passed_time":0.6067758992,"remaining_time":0.2154136661},
{"learn":[3.363405828],"iteration":738,"passed_time":0.6075471546,"remaining_time":0.2145734876},
{"learn":[3.360870533],"iteration":739,"passed_time":0.6084049002,"remaining_time":0.2137638839},
{"learn":[3.359723024],"iteration":740,"passed_time":0.6090835788,"remaining_time":0.2128915613},
{"learn":[3.357334026],"iteration":741,"passed_time":0.6097598138,"remaining_time":0.212018911},
{"learn":[3.355588041],"iteration":742,"passed_time":0.6105033865,"remaining_time":0.2111700812},
{"learn":[3.353147825],"iteration":743,"passed_time":0.6111651016,"remaining_time":0.2102933683},
{"learn":[3.347583667],"iteration":744,"passed_time":0.6120375379,"remaining_time":0.2094893586},
{"learn":[3.346430018],"iteration":745,"passed_time":0.6128343826,"remaining_time":0.2086594279},
{"learn":[3.343319676],"iteration":746,"passed_time":0.6135567077,"remaining_time":0.2078043468},
{"learn":[3.341667595],"iteration":747,"passed_time":0.6142602776,"remaining_time":0.2069433021},
{"learn":[3.340846977],"iteration":748,"passed_time":0.6149731558,"remaining_time":0.2060857972},
{"learn":[3.339784679],"iteration":749,"passed_time":0.6156571148,"remaining_time":0.2052190383},
{"learn":[3.338292965],"iteration":750,"passed_time":0.6164134326,"remaining_time":0.2043767573},
{"learn":[3.335985455],"iteration":751,"passed_time":0.6170812119,"remaining_time":0.203505506},
{"learn":[3.333998604],"iteration":752,"passed_time":0.6178333274,"remaining_time":0.2026624593},
{"learn":[3.333143773],"iteration":753,"passed_time":0.6184850706,"remaining_time":0.2017869063},
{"learn":[3.332072994],"iteration":754,"passed_time":0.6191562828,"remaining_time":0.2009182639},
{"learn":[3.330689046],"iteration":755,"passed_time":0.6198375444,"remaining_time":0.2000533873},
{"learn":[3.326825806],"iteration":756,"passed_time":0.6204596204,"remaining_time":0.199169997},
{"learn":[3.323686742],"iteration":757,"passed_time":0.6210766921,"remaining_time":0.1982856985},
{"learn":[3.322837172],"iteration":758,"passed_time":0.621697298,"remaining_time":0.1974032264},
{"learn":[3.320967681],"iteration":759,"passed_time":0.6223118579,"remaining_time":0.1965195341},
{"learn":[3.319173963],"iteration":760,"passed_time":0.623030415,"remaining_time":0.1956692105},
{"learn":[3.316990945],"iteration":761,"passed_time":0.6238122005,"remaining_time":0.1948389813},
{"learn":[3.316155158],"iteration":762,"passed_time":0.6244934801,"remaining_time":0.1939776603},
{"learn":[3.315664473],"iteration":763,"passed_time":0.6251179817,"remaining_time":0.1930992718},
{"learn":[3.31487899],"iteration":764,"passed_time":0.6257228431,"remaining_time":0.1922155139},
{"learn":[3.312262395],"iteration":765,"passed_time":0.6263637369,"remaining_time":0.1913434914},
{"learn":[3.309207141],"iteration":766,"passed_time":0.6270002188,"remaining_time":0.1904707314},
{"learn":[3.305505794],"iteration":767,"passed_time":0.6276296657,"remaining_time":0.1895964615},
{"learn":[3.302979826],"iteration":768,"passed_time":0.6282925245,"remaining_time":0.188732865},
{"learn":[3.300344106],"iteration":769,"passed_time":0.6289721683,"remaining_time":0.1878748035},
{"learn":[3.29932769],"iteration":770,"passed_time":0.6296609576,"remaining_time":0.1870199213},
{"learn":[3.297257282],"iteration":771,"passed_time":0.6303051342,"remaining_time":0.1861522935},
{"learn":[3.295001947],"iteration":772,"passed_time":0.6309450982,"remaining_time":0.1852840068},
{"learn":[3.291242052],"iteration":773,"passed_time":0.631635965,"remaining_time":0.1844311733},
{"learn":[3.290328903],"iteration":774,"passed_time":0.6322653572,"remaining_time":0.1835609102},
{"learn":[3.290175883],"iteration":775,"passed_time":0.632866783,"remaining_time":0.1826831951},
{"learn":[3.288589576],"iteration":776,"passed_time":0.6334915215,"remaining_time":0.181812882},
{"learn":[3.288324504],"iteration":777,"passed_time":0.6342079412,"remaining_time":0.1809693611},
{"learn":[3.285530631],"iteration":778,"passed_time":0.6348595115,"remaining_time":0.180107769},
{"learn":[3.282601844],"iteration":779,"passed_time":0.6355148305,"remaining_time":0.1792477727},
{"learn":[3.282481527],"iteration":780,"passed_time":0.6361414413,"remaining_time":0.1783802505},
{"learn":[3.282139044],"iteration":781,"passed_time":0.6367526754,"remaining_time":0.1775090579},
{"learn":[3.280195555],"iteration":782,"passed_time":0.637487656,"remaining_time":0.1766728242},
{"learn":[3.279317713],"iteration":783,"passed_time":0.6381592746,"remaining_time":0.175819392},
{"learn":[3.276567077],"iteration":784,"passed_time":0.638831357,"remaining_time":0.17496655},
{"learn":[3.276181469],"iteration":785,"passed_time":0.6395095238,"remaining_time":0.1741158246},
{"learn":[3.274348589],"iteration":786,"passed_time":0.640198674,"remaining_time":0.1732685103},
{"learn":[3.272180705],"iteration":787,"passed_time":0.6408443248,"remaining_time":0.1724098945},
{"learn":[3.270556981],"iteration":788,"passed_time":0.6414742284,"remaining_time":0.1715476073},
{"learn":[3.267683312],"iteration":789,"passed_time":0.6421163305,"remaining_time":0.1706891512},
{"learn":[3.265544717],"iteration":790,"passed_time":0.6427430602,"remaining_time":0.1698271802},
{"learn":[3.262957993],"iteration":791,"passed_time":0.6433733801,"remaining_time":0.1689667463},
{"learn":[3.260462894],"iteration":792,"passed_time":0.6440027647,"remaining_time":0.1681066485},
{"learn":[3.259598678],"iteration":793,"passed_time":0.6446502664,"remaining_time":0.1672518323},
{"learn":[3.257507256],"iteration":794,"passed_time":0.6453330277,"remaining_time":0.1664066298},
{"learn":[3.256402159],"iteration":795,"passed_time":0.6459979144,"remaining_time":0.1655572544},
{"learn":[3.256208852],"iteration":796,"passed_time":0.6466221157,"remaining_time":0.1646979793},
{"learn":[3.253775396],"iteration":797,"passed_time":0.6472465732,"remaining_time":0.1638393581},
{"learn":[3.253597596],"iteration":798,"passed_time":0.6478388205,"remaining_time":0.1629732202},
{"learn":[3.253388917],"iteration":799,"passed_time":0.6484617549,"remaining_time":0.1621154387},
{"learn":[3.249687157],"iteration":800,"passed_time":0.6490997647,"remaining_time":0.161261989},
{"learn":[3.249259342],"iteration":801,"passed_time":0.6497144782,"remaining_time":0.160403325},
{"learn":[3.248621694],"iteration":802,"passed_time":0.6503756558,"remaining_time":0.1595566677},
{"learn":[3.246004333],"iteration":803,"passed_time":0.6510357393,"remaining_time":0.1587102051},
{"learn":[3.244494919],"iteration":804,"passed_time":0.6516985857,"remaining_time":0.1578648748},
{"learn":[3.243324185],"iteration":805,"passed_time":0.6524018577,"remaining_time":0.1570297275},
{"learn":[3.239181089],"iteration":806,"passed_time":0.653105741,"remaining_time":0.1561950533},
{"learn":[3.23567809],"iteration":807,"passed_time":0.6541467524,"remaining_time":0.1554408124},
{"learn":[3.233695403],"iteration":808,"passed_time":0.6550735193,"remaining_time":0.1546588902},
{"learn":[3.230554133],"iteration":809,"passed_time":0.6561330148,"remaining_time":0.1539077442},
{"learn":[3.22949535],"iteration":810,"passed_time":0.6568712872,"remaining_time":0.1530809781},
{"learn":[3.229263531],"iteration":811,"passed_time":0.6575616027,"remaining_time":0.1522433267},
{"learn":[3.227228974],"iteration":812,"passed_time":0.6582453647,"remaining_time":0.1514045304},
{"learn":[3.22389102],"iteration":813,"passed_time":0.6588668025,"remaining_time":0.1505518738},
{"learn":[3.22311437],"iteration":814,"passed_time":0.6594758958,"remaining_time":0.1496969825},
{"learn":[3.222093727],"iteration":815,"passed_time":0.6601103229,"remaining_time":0.1488484061},
{"learn":[3.221082305],"iteration":816,"passed_time":0.6607707349,"remaining_time":0.1480061744},
{"learn":[3.220092485],"iteration":817,"passed_time":0.6614932759,"remaining_time":0.1471782105},
{"learn":[3.218228259],"iteration":818,"passed_time":0.6621366377,"remaining_time":0.1463330054},
{"learn":[3.216813706],"iteration":819,"passed_time":0.6627936792,"remaining_time":0.1454912954},
{"learn":[3.215556239],"iteration":820,"passed_time":0.66346464,"remaining_time":0.1446530701},
{"learn":[3.214567386],"iteration":821,"passed_time":0.6641061185,"remaining_time":0.1438088675},
{"learn":[3.212654925],"iteration":822,"passed_time":0.6647343392,"remaining_time":0.1429623062},
{"learn":[3.210500075],"iteration":823,"passed_time":0.6653780984,"remaining_time":0.1421195938},
{"learn":[3.207962273],"iteration":824,"passed_time":0.6660247409,"remaining_time":0.1412779754},
{"learn":[3.206249662],"iteration":825,"passed_time":0.6668159826,"remaining_time":0.1404672893},
{"learn":[3.205051763],"iteration":826,"passed_time":0.6674726849,"remaining_time":0.139628506},
{"learn":[3.204172569],"iteration":827,"passed_time":0.6681274277,"remaining_time":0.1387897555},
{"learn":[3.202176853],"iteration":828,"passed_time":0.6687682375,"remaining_time":0.1379485749},
{"learn":[3.201808736],"iteration":829,"passed_time":0.6693936575,"remaining_time":0.137104725},
{"learn":[3.200555809],"iteration":830,"passed_time":0.6700251858,"remaining_time":0.1362626431},
{"learn":[3.197674185],"iteration":831,"passed_time":0.6706832132,"remaining_time":0.135426418},
{"learn":[3.196780486],"iteration":832,"passed_time":0.6712692575,"remaining_time":0.1345761897},
{"learn":[3.196491413],"iteration":833,"passed_time":0.6720024946,"remaining_time":0.1337558922},
{"learn":[3.194813915],"iteration":834,"passed_time":0.6726817162,"remaining_time":0.1329251295},
{"learn":[3.192448258],"iteration":835,"passed_time":0.6733187156,"remaining_time":0.1320864466},
{"learn":[3.190135628],"iteration":836,"passed_time":0.6740136008,"remaining_time":0.1312595184},
{"learn":[3.18859344],"iteration":837,"passed_time":0.6746940077,"remaining_time":0.1304301065},
{"learn":[3.18699352],"iteration":838,"passed_time":0.6753281042,"remaining_time":0.129592163},
{"learn":[3.186907812],"iteration":839,"passed_time":0.6759406087,"remaining_time":0.1287505921},
{"learn":[3.185012372],"iteration":840,"passed_time":0.6765599394,"remaining_time":0.1279108566},
{"learn":[3.184591298],"iteration":841,"passed_time":0.6771890978,"remaining_time":0.1270734887},
{"learn":[3.182223008],"iteration":842,"passed_time":0.6778885815,"remaining_time":0.1262497121},
{"learn":[3.181156643],"iteration":843,"passed_time":0.6785399545,"remaining_time":0.1254173376},
{"learn":[3.179594049],"iteration":844,"passed_time":0.6792194644,"remaining_time":0.1245905526},
{"learn":[3.177769106],"iteration":845,"passed_time":0.6798826954,"remaining_time":0.1237611526},
{"learn":[3.176293443],"iteration":846,"passed_time":0.6805517729,"remaining_time":0.122933201},
{"learn":[3.173658446],"iteration":847,"passed_time":0.6812132067,"remaining_time":0.122104254},
{"learn":[3.171946401],"iteration":848,"passed_time":0.6818516476,"remaining_time":0.1212716122},
{"learn":[3.170312682],"iteration":849,"passed_time":0.6825122986,"remaining_time":0.1204433468},
{"learn":[3.16991],"iteration":850,"passed_time":0.6831739005,"remaining_time":0.1196156418},
{"learn":[3.168618831],"iteration":851,"passed_time":0.6838089326,"remaining_time":0.1187837113},
{"learn":[3.165994964],"iteration":852,"passed_time":0.6844905737,"remaining_time":0.1179602747},
{"learn":[3.162522214],"iteration":853,"passed_time":0.6851685942,"remaining_time":0.1171365512},
{"learn":[3.16146003],"iteration":854,"passed_time":0.6858174799,"remaining_time":0.1163082276},
{"learn":[3.160595598],"iteration":855,"passed_time":0.6864490853,"remaining_time":0.1154774162},
{"learn":[3.159762124],"iteration":856,"passed_time":0.6870778996,"remaining_time":0.114646604},
{"learn":[3.157313987],"iteration":857,"passed_time":0.6877192934,"remaining_time":0.1138183446},
{"learn":[3.154862719],"iteration":858,"passed_time":0.6883539123,"remaining_time":0.1129894082},
{"learn":[3.154156119],"iteration":859,"passed_time":0.6890591017,"remaining_time":0.1121724119},
{"learn":[3.153190318],"iteration":860,"passed_time":0.6897081444,"remaining_time":0.111346611},
{"learn":[3.149626367],"iteration":861,"passed_time":0.690390175,"remaining_time":0.1105265013},
{"learn":[3.147889955],"iteration":862,"passed_time":0.6910098776,"remaining_time":0.1096968172},
{"learn":[3.144446635],"iteration":863,"passed_time":0.6916537632,"remaining_time":0.1088714257},
{"learn":[3.142446243],"iteration":864,"passed_time":0.6922764401,"remaining_time":0.1080431438},
{"learn":[3.142246394],"iteration":865,"passed_time":0.6928835512,"remaining_time":0.1072129282},
{"learn":[3.139647249],"iteration":866,"passed_time":0.6935245466,"remaining_time":0.1063884253},
{"learn":[3.136977096],"iteration":867,"passed_time":0.6941821129,"remaining_time":0.1055668651},
{"learn":[3.136311121],"iteration":868,"passed_time":0.6948568151,"remaining_time":0.1047482656},
{"learn":[3.136249825],"iteration":869,"passed_time":0.695503646,"remaining_time":0.1039258322},
{"learn":[3.134264296],"iteration":870,"passed_time":0.696222897,"remaining_time":0.1031145278},
{"learn":[3.133310488],"iteration":871,"passed_time":0.69683268,"remaining_time":0.1022873659},
{"learn":[3.132419592],"iteration":872,"passed_time":0.6974471043,"remaining_time":0.1014613771},
{"learn":[3.130219009],"iteration":873,"passed_time":0.6980787187,"remaining_time":0.1006383507},
{"learn":[3.127763604],"iteration":874,"passed_time":0.6987393532,"remaining_time":0.0998199076},
{"learn":[3.124959364],"iteration":875,"passed_time":0.699408471,"remaining_time":0.09900302557},
{"learn":[3.124809451],"iteration":876,"passed_time":0.7000750636,"remaining_time":0.09818612637},
{"learn":[3.123165693],"iteration":877,"passed_time":0.70073509,"remaining_time":0.09736865715},
{"learn":[3.121842455],"iteration":878,"passed_time":0.701365028,"remaining_time":0.09654740431},
{"learn":[3.121184286],"iteration":879,"passed_time":0.7019872417,"remaining_time":0.09572553296},
{"learn":[3.121063272],"iteration":880,"passed_time":0.7026084264,"remaining_time":0.09490397588},
{"learn":[3.119308905],"iteration":881,"passed_time":0.7032309394,"remaining_time":0.09408305085},
{"learn":[3.118326533],"iteration":882,"passed_time":0.7038501706,"remaining_time":0.09326214038},
{"learn":[3.116244331],"iteration":883,"passed_time":0.7044808094,"remaining_time":0.09244318313},
{"learn":[3.115260191],"iteration":884,"passed_time":0.7053246257,"remaining_time":0.09165235249},
{"learn":[3.114033512],"iteration":885,"passed_time":0.7062903447,"remaining_time":0.09087708724},
{"learn":[3.112658405],"iteration":886,"passed_time":0.7072589085,"remaining_time":0.09010175497},
{"learn":[3.109586576],"iteration":887,"passed_time":0.7080197071,"remaining_time":0.08929978287},
{"learn":[3.10923454],"iteration":888,"passed_time":0.7086804962,"remaining_time":0.08848541629},
{"learn":[3.108356956],"iteration":889,"passed_time":0.7095107568,"remaining_time":0.08769234073},
{"learn":[3.106500882],"iteration":890,"passed_time":0.7103049317,"remaining_time":0.08689476718},
{"learn":[3.105288666],"iteration":891,"passed_time":0.7111646842,"remaining_time":0.08610514114},
{"learn":[3.103761961],"iteration":892,"passed_time":0.7118809448,"remaining_time":0.08529816472},
{"learn":[3.10183129],"iteration":893,"passed_time":0.7125573657,"remaining_time":0.08448666753},
{"learn":[3.099689525],"iteration":894,"passed_time":0.7131941331,"remaining_time":0.08367082008},
{"learn":[3.098045787],"iteration":895,"passed_time":0.7138277106,"remaining_time":0.08285500213},
{"learn":[3.096478809],"iteration":896,"passed_time":0.7144653513,"remaining_time":0.08204005706},
{"learn":[3.096311921],"iteration":897,"passed_time":0.7151037949,"remaining_time":0.08122559809},
{"learn":[3.094604975],"iteration":898,"passed_time":0.7159547112,"remaining_time":0.08043540137},
{"learn":[3.091751531],"iteration":899,"passed_time":0.7167144254,"remaining_time":0.07963493616},
{"learn":[3.089765858],"iteration":900,"passed_time":0.7173635418,"remaining_time":0.07882240914},
{"learn":[3.087262769],"iteration":901,"passed_time":0.718009756,"remaining_time":0.07800992914},
{"learn":[3.086169934],"iteration":902,"passed_time":0.7186758582,"remaining_time":0.07719995376},
{"learn":[3.083629236],"iteration":903,"passed_time":0.7193921432,"remaining_time":0.07639562583},
{"learn":[3.081353214],"iteration":904,"passed_time":0.7200275204,"remaining_time":0.07558299938},
{"learn":[3.080429779],"iteration":905,"passed_time":0.7206771471,"remaining_time":0.07477224264},
{"learn":[3.077513717],"iteration":906,"passed_time":0.7215029617,"remaining_time":0.07397990677},
{"learn":[3.075920533],"iteration":907,"passed_time":0.7222440151,"remaining_time":0.07317890901},
{"learn":[3.074138999],"iteration":908,"passed_time":0.7230161937,"remaining_time":0.0723811591},
{"learn":[3.072360269],"iteration":909,"passed_time":0.7236589132,"remaining_time":0.07157066175},
{"learn":[3.072105366],"iteration":910,"passed_time":0.7243148331,"remaining_time":0.07076182234},
{"learn":[3.069607047],"iteration":911,"passed_time":0.7250327886,"remaining_time":0.06995930417},
{"learn":[3.069103985],"iteration":912,"passed_time":0.7256980238,"remaining_time":0.0691519475},
{"learn":[3.06808215],"iteration":913,"passed_time":0.7263100672,"remaining_time":0.06833989691},
{"learn":[3.068010182],"iteration":914,"passed_time":0.7270680472,"remaining_time":0.06754184045},
{"learn":[3.067569405],"iteration":915,"passed_time":0.727797256,"remaining_time":0.06674123308},
{"learn":[3.067061041],"iteration":916,"passed_time":0.728474334,"remaining_time":0.06593606294},
{"learn":[3.066151486],"iteration":917,"passed_time":0.7291144709,"remaining_time":0.06512787212},
{"learn":[3.065418818],"iteration":918,"passed_time":0.7297216657,"remaining_time":0.06431714355},
{"learn":[3.062959602],"iteration":919,"passed_time":0.7303274283,"remaining_time":0.0635067329},
{"learn":[3.061929739],"iteration":920,"passed_time":0.7309520969,"remaining_time":0.06269838834},
{"learn":[3.061120223],"iteration":921,"passed_time":0.7315647254,"remaining_time":0.06188942362},
{"learn":[3.060659718],"iteration":922,"passed_time":0.7322906239,"remaining_time":0.06109033374},
{"learn":[3.059128946],"iteration":923,"passed_time":0.7333447709,"remaining_time":0.06031840107},
{"learn":[3.056115683],"iteration":924,"passed_time":0.7342901331,"remaining_time":0.05953703782},
{"learn":[3.05491918],"iteration":925,"passed_time":0.7349404772,"remaining_time":0.0587317444},
{"learn":[3.051864677],"iteration":926,"passed_time":0.7356031059,"remaining_time":0.05792775267},
{"learn":[3.050964525],"iteration":927,"passed_time":0.7362228354,"remaining_time":0.05712073723},
{"learn":[3.048469109],"iteration":928,"passed_time":0.73684584,"remaining_time":0.05631437529},
{"learn":[3.047720352],"iteration":929,"passed_time":0.7375855656,"remaining_time":0.05551719311},
{"learn":[3.046701754],"iteration":930,"passed_time":0.7384260646,"remaining_time":0.05472760307},
{"learn":[3.044472512],"iteration":931,"passed_time":0.7391463914,"remaining_time":0.05392913585},
{"learn":[3.042759475],"iteration":932,"passed_time":0.7397968632,"remaining_time":0.05312581976},
{"learn":[3.04145677],"iteration":933,"passed_time":0.7404391344,"remaining_time":0.05232225147},
{"learn":[3.041387627],"iteration":934,"passed_time":0.7410579403,"remaining_time":0.05151739692},
{"learn":[3.038050439],"iteration":935,"passed_time":0.7417091267,"remaining_time":0.05071515396},
{"learn":[3.035745153],"iteration":936,"passed_time":0.7423537172,"remaining_time":0.04991278995},
{"learn":[3.035465344],"iteration":937,"passed_time":0.7429600222,"remaining_time":0.04910823174},
{"learn":[3.033404992],"iteration":938,"passed_time":0.7436287019,"remaining_time":0.04830814784},
{"learn":[3.033269966],"iteration":939,"passed_time":0.744326977,"remaining_time":0.04751023257},
{"learn":[3.032561947],"iteration":940,"passed_time":0.7449611458,"remaining_time":0.04670850967},
{"learn":[3.031487779],"iteration":941,"passed_time":0.7455847744,"remaining_time":0.04590649354},
{"learn":[3.0296518],"iteration":942,"passed_time":0.7461992645,"remaining_time":0.04510430337},
{"learn":[3.029200851],"iteration":943,"passed_time":0.746776123,"remaining_time":0.04430027848},
{"learn":[3.028403679],"iteration":944,"passed_time":0.7473916816,"remaining_time":0.04349898676},
{"learn":[3.025833763],"iteration":945,"passed_time":0.7480054596,"remaining_time":0.04269798606},
{"learn":[3.02463592],"iteration":946,"passed_time":0.7487662846,"remaining_time":0.04190561044},
{"learn":[3.02286627],"iteration":947,"passed_time":0.7495066114,"remaining_time":0.041112177},
{"learn":[3.022546681],"iteration":948,"passed_time":0.7501682291,"remaining_time":0.04031462559},
{"learn":[3.022301308],"iteration":949,"passed_time":0.7508181988,"remaining_time":0.0395167473},
{"learn":[3.020340666],"iteration":950,"passed_time":0.7514425888,"remaining_time":0.0387178621},
{"learn":[3.018518258],"iteration":951,"passed_time":0.7520354039,"remaining_time":0.03791775146},
{"learn":[3.017523154],"iteration":952,"passed_time":0.7526359337,"remaining_time":0.03711845633},
{"learn":[3.016339643],"iteration":953,"passed_time":0.7533185762,"remaining_time":0.03632353722},
{"learn":[3.015748253],"iteration":954,"passed_time":0.7539199038,"remaining_time":0.03552502164},
{"learn":[3.014165297],"iteration":955,"passed_time":0.7545847037,"remaining_time":0.03472983992},
{"learn":[3.012314296],"iteration":956,"passed_time":0.755222199,"remaining_time":0.03393370382},
{"learn":[3.010870586],"iteration":957,"passed_time":0.7558614895,"remaining_time":0.03313797762},
{"learn":[3.010231564],"iteration":958,"passed_time":0.756464469,"remaining_time":0.03234102526},
{"learn":[3.008504861],"iteration":959,"passed_time":0.757074576,"remaining_time":0.031544774},
{"learn":[3.007821587],"iteration":960,"passed_time":0.7576596878,"remaining_time":0.03074789576},
{"learn":[3.006373137],"iteration":961,"passed_time":0.7583313793,"remaining_time":0.02995487777},
{"learn":[3.004602418],"iteration":962,"passed_time":0.7589493609,"remaining_time":0.02916004813},
{"learn":[3.001491918],"iteration":963,"passed_time":0.7595761607,"remaining_time":0.02836591472},
{"learn":[2.999403649],"iteration":964,"passed_time":0.7602332979,"remaining_time":0.02757322842},
{"learn":[2.999266536],"iteration":965,"passed_time":0.7608265631,"remaining_time":0.02677857468},
{"learn":[2.997935055],"iteration":966,"passed_time":0.7614082481,"remaining_time":0.02598394228},
{"learn":[2.996149752],"iteration":967,"passed_time":0.76200569,"remaining_time":0.02519027074},
{"learn":[2.995908723],"iteration":968,"passed_time":0.7626164118,"remaining_time":0.02439742907},
{"learn":[2.99380082],"iteration":969,"passed_time":0.7632118478,"remaining_time":0.02360449014},
{"learn":[2.992369625],"iteration":970,"passed_time":0.7638116661,"remaining_time":0.02281208889},
{"learn":[2.991394625],"iteration":971,"passed_time":0.7644237918,"remaining_time":0.02202043845},
{"learn":[2.989096243],"iteration":972,"passed_time":0.7651704857,"remaining_time":0.02123289118},
{"learn":[2.986671028],"iteration":973,"passed_time":0.765833819,"remaining_time":0.02044320256},
{"learn":[2.986052869],"iteration":974,"passed_time":0.7664283845,"remaining_time":0.01965200986},
{"learn":[2.985512661],"iteration":975,"passed_time":0.7670335303,"remaining_time":0.01886148025},
{"learn":[2.983628619],"iteration":976,"passed_time":0.7677693618,"remaining_time":0.01807440668},
{"learn":[2.981870278],"iteration":977,"passed_time":0.7683945081,"remaining_time":0.01728494803},
{"learn":[2.979838813],"iteration":978,"passed_time":0.7690104758,"remaining_time":0.01649562818},
{"learn":[2.978982604],"iteration":979,"passed_time":0.7696202134,"remaining_time":0.01570653497},
{"learn":[2.97736168],"iteration":980,"passed_time":0.7702265914,"remaining_time":0.01491774234},
{"learn":[2.974159799],"iteration":981,"passed_time":0.7708948421,"remaining_time":0.01413045535},
{"learn":[2.972657328],"iteration":982,"passed_time":0.7715300009,"remaining_time":0.01334283827},
{"learn":[2.971256833],"iteration":983,"passed_time":0.7721452069,"remaining_time":0.01255520662},
{"learn":[2.9707456],"iteration":984,"passed_time":0.7727507784,"remaining_time":0.01176777835},
{"learn":[2.968502202],"iteration":985,"passed_time":0.7733695447,"remaining_time":0.01098090631},
{"learn":[2.9665629],"iteration":986,"passed_time":0.7739590037,"remaining_time":0.0101939889},
{"learn":[2.964661207],"iteration":987,"passed_time":0.7745507661,"remaining_time":0.009407499183},
{"learn":[2.963724931],"iteration":988,"passed_time":0.7751607302,"remaining_time":0.008621605695},
{"learn":[2.962972785],"iteration":989,"passed_time":0.7757464339,"remaining_time":0.007835822565},
{"learn":[2.961088079],"iteration":990,"passed_time":0.7764544874,"remaining_time":0.007051554376},
{"learn":[2.959331015],"iteration":991,"passed_time":0.7770738343,"remaining_time":0.00626672447},
{"learn":[2.958920061],"iteration":992,"passed_time":0.7776599905,"remaining_time":0.005481993891},
{"learn":[2.958679155],"iteration":993,"passed_time":0.7782518606,"remaining_time":0.004697697348},
{"learn":[2.957284129],"iteration":994,"passed_time":0.778869577,"remaining_time":0.003913917472},
{"learn":[2.956422123],"iteration":995,"passed_time":0.7794589144,"remaining_time":0.003130357086},
{"learn":[2.954786645],"iteration":996,"passed_time":0.7800578839,"remaining_time":0.002347215297},
{"learn":[2.952613544],"iteration":997,"passed_time":0.780658291,"remaining_time":0.001564445473},
{"learn":[2.952196863],"iteration":998,"passed_time":0.7812326739,"remaining_time":0.0007820146886},
{"learn":[2.950989284],"iteration":999,"passed_time":0.7820222785,"remaining_time":0}
]}